Workbook

Sheet Resumen
B1: 45809 | C1: Metros
A2: Almacen | B2: =Almacén_MateriaPrima!E150 -> 142797.79
A3: Agujetas / Material activo | B3: =+Agujeta!I168 -> 525808.15
A4: Agujetas / Material inactivo | B4: =Agujeta!I169 -> 223244.92
A5: Caja Individual / Material activo | B5: ='Caja Individual'!E57 -> 135552.4
A6: Caja individual / Material inactivo | B6: ='Caja Individual'!E58 -> 328142.7
A7: Caja Emb | B7: =+Caja_Embarque!J48 -> 73467.378
A8: Etiquetas | B8: =+Tabla3[[#Totals],[Total]] -> 63647.386
A9: Hulera / Material activo | B9: =+Hulera!F55 -> 199063.94
A10: Hulera / Material Inactivo | B10: =Hulera!F56 -> 76760.92
A11: Cargas/hule | B11: =+ROLLOS[[#Totals],[Total]] -> 142656
A12: Suela/inventario/con movimiento | B12: =+Tabla11312[[#Totals],[TOTAL]] -> 18620.65
A13: Suela/inventario/sin movimiento | B13: =+Tabla113[[#Totals],[TOTAL]] -> 664417.85 | D13: Aprox
A14: Tela Virgen / activo | B14: =Inv_TelaVirgenMov!E43 -> 967492.29 | D14: No cuento con precios del Drill
A15: Tela Virgen / inactivo | B15: =+Tabla7[[#Totals],[TOTAL]] -> 3797454.9 | D15: No cuento con precios de algunos materiales
A16: TelaNoAprovechable | B16: =+TelaNoUtilizable!E22 -> 0 | C16: =TelaNoUtilizable!C22 -> 1757 | D16: No cuento con precios de algunos materiales
B18: =SUM(B2:B17) -> 7359127.3 | C18: No incluye IVA

Sheet Inv_TelaVirgenMov
A1: CÓDIGO | B1: DESCRIPCIÓN | C1: METROS | D1: PRECIO X METRO | E1: TOTAL | F1: PRECIO NO INCLUYE IVA
A2: 511 | B2: 511453 AZ25211 | C2: 108 | D2: 67.89 | E2: =Tabla6[[#This Row],[METROS]]*Tabla6[[#This Row],[PRECIO X METRO]] -> 7332.12
A3: 511 | B3: 511473 VE27149 CHIVE | C3: 305 | D3: 67.89 | E3: =Tabla6[[#This Row],[METROS]]*Tabla6[[#This Row],[PRECIO X METRO]] -> 20706.45
A4: 511 | B4: 511426 RO23174 BLOODY RED | C4: 92 | D4: 67.89 | E4: =Tabla6[[#This Row],[METROS]]*Tabla6[[#This Row],[PRECIO X METRO]] -> 6245.88
A5: 511 | B5: 511479 GRIS SMOKED PEARL | C5: 104 | D5: 67.89 | E5: =Tabla6[[#This Row],[METROS]]*Tabla6[[#This Row],[PRECIO X METRO]] -> 7060.56
A6: 511 | B6: LONA BLANCO ESTRELLA 10016 CAUTIFICADO | C6: 512 | D6: 81.78 | E6: =Tabla6[[#This Row],[METROS]]*Tabla6[[#This Row],[PRECIO X METRO]] -> 41871.36
A7: 511 | B7: LONA NEGRA 511 / 79004 CA:42732 | C7: 892 | D7: 86.49 | E7: =Tabla6[[#This Row],[METROS]]*Tabla6[[#This Row],[PRECIO X METRO]] -> 77149.08
A8: 511 | B8: 511314 RO2338 BUGAMBILIA | C8: 195 | D8: 67.89 | E8: =Tabla6[[#This Row],[METROS]]*Tabla6[[#This Row],[PRECIO X METRO]] -> 13238.55
A9: 582 | B9: NUEVA CANASTA NEGRO 79004 C.582270 | C9: 252 | D9: 85.5 | E9: =Tabla6[[#This Row],[METROS]]*Tabla6[[#This Row],[PRECIO X METRO]] -> 21546
A10: 633 | B10: 633582 AZ 25211 BLUE BERRY | C10: 266 | D10: 57.85 | E10: =Tabla6[[#This Row],[METROS]]*Tabla6[[#This Row],[PRECIO X METRO]] -> 15388.1
A11: 633 | B11: 633583 BAL GRAY 28047 | C11: 494 | D11: 57.85 | E11: =Tabla6[[#This Row],[METROS]]*Tabla6[[#This Row],[PRECIO X METRO]] -> 28577.9
A12: 633 | B12: 633589 RO23176 CHILLI PEPPER | C12: 1061 | D12: 57.85 | E12: =Tabla6[[#This Row],[METROS]]*Tabla6[[#This Row],[PRECIO X METRO]] -> 61378.85
A13: 633 | B13: 633598 NGO 79004 | C13: 308 | D13: 57.85 | E13: =Tabla6[[#This Row],[METROS]]*Tabla6[[#This Row],[PRECIO X METRO]] -> 17817.8
... A15: 651 | B15: 651137 AZ25207 BAL NAVY | C15: 570 | D15: 79.05 | E15: =Tabla6[[#This Row],[METROS]]*Tabla6[[#This Row],[PRECIO X METRO]] -> 45058.5
A16: 651 | B16: PLIX TAWNY PORT 651171 RO23182 | C16: =15+1176 -> 1191 | D16: 79.05 | E16: =Tabla6[[#This Row],[METROS]]*Tabla6[[#This Row],[PRECIO X METRO]] -> 94148.55
A17: 651 | B17: 651110 NEGRO 29016 | C17: 3 | D17: 79.05 | E17: =Tabla6[[#This Row],[METROS]]*Tabla6[[#This Row],[PRECIO X METRO]] -> 237.15
A18: 651 | B18: 651111 CHILLI PAPPER 23176 | C18: 717 | D18: 79.05 | E18: =Tabla6[[#This Row],[METROS]]*Tabla6[[#This Row],[PRECIO X METRO]] -> 56678.85
A19: 651 | B19: 651136 GR 28047 BAL GREY | C19: 82 | D19: 79.05 | E19: =Tabla6[[#This Row],[METROS]]*Tabla6[[#This Row],[PRECIO X METRO]] -> 6482.1
A20: 651 | B20: PLIX CHARCOAL GREY 651177 | C20: 225 | D20: 86.49 | E20: =Tabla6[[#This Row],[METROS]]*Tabla6[[#This Row],[PRECIO X METRO]] -> 19460.25
A21: 668 | B21: 6 OZ WILL DOVE | C21: 20 | D21: 80.75 | E21: =Tabla6[[#This Row],[METROS]]*Tabla6[[#This Row],[PRECIO X METRO]] -> 1615
A22: 668 | B22: 668052 GR 28069 GLACIER GRAY | C22: 74 | D22: 80.75 | E22: =Tabla6[[#This Row],[METROS]]*Tabla6[[#This Row],[PRECIO X METRO]] -> 5975.5
A23: 668 | B23: 6OZ BLACK | C23: 30 | D23: 80.75 | E23: =Tabla6[[#This Row],[METROS]]*Tabla6[[#This Row],[PRECIO X METRO]] -> 2422.5
A24: 668 | B24: 6OZ VANS NEGRO | C24: 15 | D24: 80.75 | E24: =Tabla6[[#This Row],[METROS]]*Tabla6[[#This Row],[PRECIO X METRO]] -> 1211.25
A25: 668 | B25: 6OZ BLANCA BLUE WAHS WHITE DC 668021 | C25: 100 | D25: 84.89 | E25: =Tabla6[[#This Row],[METROS]]*Tabla6[[#This Row],[PRECIO X METRO]] -> 8489
A26: 668 | B26: 6OZ NEGRA / BLACK | C26: 75 | D26: 80.75 | E26: =Tabla6[[#This Row],[METROS]]*Tabla6[[#This Row],[PRECIO X METRO]] -> 6056.25
A27: 668 | B27: 6OZ NEGRA DC 668008 29016 BLACK S/A | C27: 822 | D27: 80.75 | E27: =Tabla6[[#This Row],[METROS]]*Tabla6[[#This Row],[PRECIO X METRO]] -> 66376.5
A28: 674 | B28: AWAT | C28: 1525 | D28: 45.38 | E28: =Tabla6[[#This Row],[METROS]]*Tabla6[[#This Row],[PRECIO X METRO]] -> 69204.5
A29: Drill | B29: DRILL CRUDO VANS | C29: 30 | E29: =Tabla6[[#This Row],[METROS]]*Tabla6[[#This Row],[PRECIO X METRO]] -> 0
A30: Látex | B30: LATEX | C30: =(22)*35 -> 770 | D30: 114.73 | E30: =Tabla6[[#This Row],[METROS]]*Tabla6[[#This Row],[PRECIO X METRO]] -> 88342.1
A31: Sarga | B31: ALICANTE | C31: 125 | D31: 26.7241 | E31: =Tabla6[[#This Row],[METROS]]*Tabla6[[#This Row],[PRECIO X METRO]] -> 3340.5125
A32: Sarga | B32: GABARDINA BLANCA C/A | C32: 50 | D32: 57.1 | E32: =Tabla6[[#This Row],[METROS]]*Tabla6[[#This Row],[PRECIO X METRO]] -> 2855
A33: Sarga | B33: GABARDINA NEGRA C/A | C33: 170 | D33: 64.21 | E33: =Tabla6[[#This Row],[METROS]]*Tabla6[[#This Row],[PRECIO X METRO]] -> 10915.7
A34: Sarga | B34: GABARDINA NEGRA S/A | C34: 500 | D34: 61.47 | E34: =Tabla6[[#This Row],[METROS]]*Tabla6[[#This Row],[PRECIO X METRO]] -> 30735
A35: Sarga | B35: GABARDINA CRUDA C/A | C35: 300 | D35: 43.64 | E35: =Tabla6[[#This Row],[METROS]]*Tabla6[[#This Row],[PRECIO X METRO]] -> 13092
A36: Sarga | B36: TOLEDO | C36: 0 | D36: 31.0344 | E36: =Tabla6[[#This Row],[METROS]]*Tabla6[[#This Row],[PRECIO X METRO]] -> 0
A37: Sarga | B37: BARCELONA | C37: 59 | D37: 12.931 | E37: =Tabla6[[#This Row],[METROS]]*Tabla6[[#This Row],[PRECIO X METRO]] -> 762.929
A38: Sarga | B38: SERGE | C38: 300 | D38: 27.756 | E38: =Tabla6[[#This Row],[METROS]]*Tabla6[[#This Row],[PRECIO X METRO]] -> 8326.8
A39: Látex | B39: CRUDA | C39: 0 | D39: 190.2 | E39: =Tabla6[[#This Row],[METROS]]*Tabla6[[#This Row],[PRECIO X METRO]] -> 0
A40: Látex | B40: NEGRA | C40: 475 | D40: 207.58 | E40: =Tabla6[[#This Row],[METROS]]*Tabla6[[#This Row],[PRECIO X METRO]] -> 98600.5
C43: =SUM(C2:C40) -> 12969 | E43: =SUM(E2:E40) -> 967492.29
C46: =21*35 -> 735

Sheet Inv_TelaVirgen_SinMov
A1: CÓDIGO | B1: DESCRIPCIÓN | C1: METROS FISCAL | D1: METROS REAL | E1: PRECIO X METROS | F1: TOTAL | G1: OBS
A2: 511 | B2: 511 ROSA PALO41 | C2: 41 | E2: 67.89 | F2: =Tabla7[[#This Row],[METROS FISCAL]]*Tabla7[[#This Row],[PRECIO X METROS]] -> 2783.49
A3: 511 | B3: 511463 VI26054 GRAPE WIND | C3: 79 | E3: 67.89 | F3: =Tabla7[[#This Row],[METROS FISCAL]]*Tabla7[[#This Row],[PRECIO X METROS]] -> 5363.31
A4: 511 | B4: 511501 AZ25220 MIDNIGHT | C4: 110 | E4: 67.89 | F4: =Tabla7[[#This Row],[METROS FISCAL]]*Tabla7[[#This Row],[PRECIO X METROS]] -> 7467.9
A5: 511 | B5: 511461 GR28056 PALOMA | C5: 150 | E5: 67.89 | F5: =Tabla7[[#This Row],[METROS FISCAL]]*Tabla7[[#This Row],[PRECIO X METROS]] -> 10183.5
A6: 511 | B6: AZUL TURQUEZA | C6: 68 | E6: 67.89 | F6: =Tabla7[[#This Row],[METROS FISCAL]]*Tabla7[[#This Row],[PRECIO X METROS]] -> 4616.52
A7: 511 | B7: CHARCOAL GRAY 28064 | C7: 319 | E7: 79.271 | F7: =Tabla7[[#This Row],[METROS FISCAL]]*Tabla7[[#This Row],[PRECIO X METROS]] -> 25287.449
A8: 511 | B8: GREY | C8: 25 | E8: 67.89 | F8: =Tabla7[[#This Row],[METROS FISCAL]]*Tabla7[[#This Row],[PRECIO X METROS]] -> 1697.25
A9: 511 | B9: PLUMBAGO | C9: 20 | E9: 67.89 | F9: =Tabla7[[#This Row],[METROS FISCAL]]*Tabla7[[#This Row],[PRECIO X METROS]] -> 1357.8
A10: 511 | B10: VINO | C10: 70 | E10: 67.89 | F10: =Tabla7[[#This Row],[METROS FISCAL]]*Tabla7[[#This Row],[PRECIO X METROS]] -> 4752.3
A11: 582 | B11: NUEVA CANASTA BLANCA | C11: 256 | E11: 78 | F11: =Tabla7[[#This Row],[METROS FISCAL]]*Tabla7[[#This Row],[PRECIO X METROS]] -> 19968
A12: 633 | B12: 633 BUCKTHORN 24134 | C12: 234 | E12: 57.85 | F12: =Tabla7[[#This Row],[METROS FISCAL]]*Tabla7[[#This Row],[PRECIO X METROS]] -> 13536.9
A13: 633 | B13: 633597 VI 26053 ULTRAVIOLET AP/LIG 3% | C13: 143 | E13: 57.85 | F13: =Tabla7[[#This Row],[METROS FISCAL]]*Tabla7[[#This Row],[PRECIO X METROS]] -> 8272.55
... A31: 651 | B31: 651119 CR24118 CORIANDER | C31: 109 | E31: 79.05 | F31: =Tabla7[[#This Row],[METROS FISCAL]]*Tabla7[[#This Row],[PRECIO X METROS]] -> 8616.45
A32: 651 | B32: 651167 CHIVE 27149 | C32: =119+30 -> 149 | E32: 79.05 | F32: =Tabla7[[#This Row],[METROS FISCAL]]*Tabla7[[#This Row],[PRECIO X METROS]] -> 11778.45
A33: 651 | B33: 651178 CAMEO ROSE 22057 | C33: 53 | E33: 79.05 | F33: =Tabla7[[#This Row],[METROS FISCAL]]*Tabla7[[#This Row],[PRECIO X METROS]] -> 4189.65
A34: 651 | B34: 651186 CATHAY SPICE | C34: 116 | E34: 79.05 | F34: =Tabla7[[#This Row],[METROS FISCAL]]*Tabla7[[#This Row],[PRECIO X METROS]] -> 9169.8
A35: 651 | B35: AQUA | C35: 5 | E35: 79.05 | F35: =Tabla7[[#This Row],[METROS FISCAL]]*Tabla7[[#This Row],[PRECIO X METROS]] -> 395.25
A36: 651 | B36: ASH | C36: 15 | E36: 79.05 | F36: =Tabla7[[#This Row],[METROS FISCAL]]*Tabla7[[#This Row],[PRECIO X METROS]] -> 1185.75
A37: 651 | B37: BAL GREY | C37: 106 | E37: 79.05 | F37: =Tabla7[[#This Row],[METROS FISCAL]]*Tabla7[[#This Row],[PRECIO X METROS]] -> 8379.3
A38: 651 | B38: OFF WHITE / CHINA | C38: 1487 | E38: 79.05 | F38: =Tabla7[[#This Row],[METROS FISCAL]]*Tabla7[[#This Row],[PRECIO X METROS]] -> 117547.35
A39: 651 | B39: PLIX AZUL CIELO MUESTRARIO COLOR | C39: 48 | E39: 79.05 | F39: =Tabla7[[#This Row],[METROS FISCAL]]*Tabla7[[#This Row],[PRECIO X METROS]] -> 3794.4
A40: 651 | B40: PLIX BAL NAVY | C40: 30 | E40: 79.05 | F40: =Tabla7[[#This Row],[METROS FISCAL]]*Tabla7[[#This Row],[PRECIO X METROS]] -> 2371.5
A41: 651 | B41: PLIX MOSTAZA SPERRY | C41: 80 | E41: 79.05 | F41: =Tabla7[[#This Row],[METROS FISCAL]]*Tabla7[[#This Row],[PRECIO X METROS]] -> 6324
A42: 651 | B42: PLIX ROSADO FLAMEADO 23103 651174 | C42: 82 | E42: 65.0049 | F42: =Tabla7[[#This Row],[METROS FISCAL]]*Tabla7[[#This Row],[PRECIO X METROS]] -> 5330.4018
A43: 651 | B43: ROJO-10 | C43: 10 | E43: 79.05 | F43: =Tabla7[[#This Row],[METROS FISCAL]]*Tabla7[[#This Row],[PRECIO X METROS]] -> 790.5
A44: 651 | B44: TWILL CHOCOLATE | C44: 1902 | E44: 79.05 | F44: =Tabla7[[#This Row],[METROS FISCAL]]*Tabla7[[#This Row],[PRECIO X METROS]] -> 150353.1
... A89: 1000 | B89: LONA 1000 C/A AZABACHE | C89: 95 | E89: 110.1476 | F89: =Tabla7[[#This Row],[METROS FISCAL]]*Tabla7[[#This Row],[PRECIO X METROS]] -> 10464.022
A90: - | B90: CAMO RED RDBK | C90: 28 | E90: 80.75 | F90: =Tabla7[[#This Row],[METROS FISCAL]]*Tabla7[[#This Row],[PRECIO X METROS]] -> 2261
A91: - | B91: CHAMBRAY AZUL | C91: 449.7248 | F91: =Tabla7[[#This Row],[METROS FISCAL]]*Tabla7[[#This Row],[PRECIO X METROS]] -> 0
A92: - | B92: DIGITAL PRINT GRIDS LMCC | C92: 80 | E92: 80.75 | F92: =Tabla7[[#This Row],[METROS FISCAL]]*Tabla7[[#This Row],[PRECIO X METROS]] -> 6460
A93: - | B93: DIGITAL PRINT GRIDS WBK | C93: 30 | E93: 80.75 | F93: =Tabla7[[#This Row],[METROS FISCAL]]*Tabla7[[#This Row],[PRECIO X METROS]] -> 2422.5
A94: - | B94: LONA AZUL CHINA (ANCHO) | C94: 162 | F94: =Tabla7[[#This Row],[METROS FISCAL]]*Tabla7[[#This Row],[PRECIO X METROS]] -> 0
A95: - | B95: LONA BRAMANTE S/A BLANCO PAM | C95: 1045.5 | E95: 52.5356 | F95: =Tabla7[[#This Row],[METROS FISCAL]]*Tabla7[[#This Row],[PRECIO X METROS]] -> 54925.97
A96: - | B96: LONA VERDE CHINA (ANCHO) | C96: 279 | F96: =Tabla7[[#This Row],[METROS FISCAL]]*Tabla7[[#This Row],[PRECIO X METROS]] -> 0
A97: - | B97: METALLIC ROSE | C97: 163.2416 | F97: =Tabla7[[#This Row],[METROS FISCAL]]*Tabla7[[#This Row],[PRECIO X METROS]] -> 0
A98: - | B98: METALLIC SILVER | C98: 222.452 | F98: =Tabla7[[#This Row],[METROS FISCAL]]*Tabla7[[#This Row],[PRECIO X METROS]] -> 0
A99: - | B99: MEZCLILLA CHINA | C99: 922 | F99: =Tabla7[[#This Row],[METROS FISCAL]]*Tabla7[[#This Row],[PRECIO X METROS]] -> 0
A100: - | B100: POLY CANVAS DIGITAL PRINT GRIDS TQMT | C100: 43.8 | E100: 110.89 | F100: =Tabla7[[#This Row],[METROS FISCAL]]*Tabla7[[#This Row],[PRECIO X METROS]] -> 4856.982
A101: - | B101: RAYAS MARINO APLICACION BASE DN | C101: 84 | E101: 42.83 | F101: =Tabla7[[#This Row],[METROS FISCAL]]*Tabla7[[#This Row],[PRECIO X METROS]] -> 3597.72 | G101: 42402
A102: - | B102: TARTÁN CAFÉ | C102: 797 | F102: =Tabla7[[#This Row],[METROS FISCAL]]*Tabla7[[#This Row],[PRECIO X METROS]] -> 0
A103: - | B103: TELA CAFÉ CHINA | C103: 1080 | F103: =Tabla7[[#This Row],[METROS FISCAL]]*Tabla7[[#This Row],[PRECIO X METROS]] -> 0
A104: - | B104: TELA GRIS AE | C104: 1559.4 | F104: =Tabla7[[#This Row],[METROS FISCAL]]*Tabla7[[#This Row],[PRECIO X METROS]] -> 0
A105: 8oz | B105: 8OZ CAMO BKL | C105: 20 | E105: 80.75 | F105: =Tabla7[[#This Row],[METROS FISCAL]]*Tabla7[[#This Row],[PRECIO X METROS]] -> 1615
A106: 8oz | B106: 8OZ CAMO GREEN | C106: 10 | E106: 80.75 | F106: =Tabla7[[#This Row],[METROS FISCAL]]*Tabla7[[#This Row],[PRECIO X METROS]] -> 807.5
A107: 8oz | B107: 8OZ CAMO RED RDBK | C107: 225.56 | E107: 80.75 | F107: =Tabla7[[#This Row],[METROS FISCAL]]*Tabla7[[#This Row],[PRECIO X METROS]] -> 18213.97
A108: 8oz | B108: 8OZ SKECHERS AZUL CLARO | C108: 45 | E108: 80.75 | F108: =Tabla7[[#This Row],[METROS FISCAL]]*Tabla7[[#This Row],[PRECIO X METROS]] -> 3633.75
A109: 8oz | B109: 8OZ SKECHERS BLUE | C109: 195.156 | E109: 80.75 | F109: =Tabla7[[#This Row],[METROS FISCAL]]*Tabla7[[#This Row],[PRECIO X METROS]] -> 15758.847
A110: B12 | B110: B12 AZURE LT | C110: 770 | D110: 770 | E110: 154.81 | F110: =Tabla7[[#This Row],[METROS FISCAL]]*Tabla7[[#This Row],[PRECIO X METROS]] -> 119203.7 | G110: Factura a Luis
A111: B12 | B111: B12 BEIGE ALMOND | C111: 124 | D111: 124 | E111: 154.81 | F111: =Tabla7[[#This Row],[METROS FISCAL]]*Tabla7[[#This Row],[PRECIO X METROS]] -> 19196.44 | G111: Factura a Luis
A112: B12 | B112: B12 BLANCO | C112: 4917 | D112: 4917 | E112: 137.05 | F112: =Tabla7[[#This Row],[METROS FISCAL]]*Tabla7[[#This Row],[PRECIO X METROS]] -> 673874.85 | G112: Factura a Luis
A113: B12 | B113: B12 BLUE NAVY | C113: 509 | D113: 509 | E113: 154.81 | F113: =Tabla7[[#This Row],[METROS FISCAL]]*Tabla7[[#This Row],[PRECIO X METROS]] -> 78798.29 | G113: Factura a Luis
A114: B12 | B114: B12 GREY COLUMBA | C114: 91 | D114: 91 | E114: 154.81 | F114: =Tabla7[[#This Row],[METROS FISCAL]]*Tabla7[[#This Row],[PRECIO X METROS]] -> 14087.71
A115: B12 | B115: B12 GREY SAGE | C115: 198 | D115: 198 | E115: 154.81 | F115: =Tabla7[[#This Row],[METROS FISCAL]]*Tabla7[[#This Row],[PRECIO X METROS]] -> 30652.38
A116: B12 | B116: B12 LT GREY | C116: 456 | D116: 456 | E116: 154.81 | F116: =Tabla7[[#This Row],[METROS FISCAL]]*Tabla7[[#This Row],[PRECIO X METROS]] -> 70593.36 | G116: Factura a Luis
A117: B12 | B117: B12 NAVY | C117: 31 | D117: 31 | E117: 154.81 | F117: =Tabla7[[#This Row],[METROS FISCAL]]*Tabla7[[#This Row],[PRECIO X METROS]] -> 4799.11
A118: B12 | B118: B12 NEGRO | C118: 578 | D118: 578 | E118: 154.81 | F118: =Tabla7[[#This Row],[METROS FISCAL]]*Tabla7[[#This Row],[PRECIO X METROS]] -> 89480.18 | G118: Factura a Luis
A119: B12 | B119: B12 PINK SKIN | C119: 209 | D119: 209 | E119: 154.81 | F119: =Tabla7[[#This Row],[METROS FISCAL]]*Tabla7[[#This Row],[PRECIO X METROS]] -> 32355.29
A120: B12 | B120: B12 WHITE AVORIO | C120: 504 | D120: 504 | E120: 154.81 | F120: =Tabla7[[#This Row],[METROS FISCAL]]*Tabla7[[#This Row],[PRECIO X METROS]] -> 78024.24
A121: B2 | B121: B2 AZURE LT | C121: 497 | D121: 497 | E121: 70.91 | F121: =Tabla7[[#This Row],[METROS FISCAL]]*Tabla7[[#This Row],[PRECIO X METROS]] -> 35242.27
A122: B2 | B122: B2 BEIGE ALMOND | C122: 90 | D122: 90 | E122: 70.91 | F122: =Tabla7[[#This Row],[METROS FISCAL]]*Tabla7[[#This Row],[PRECIO X METROS]] -> 6381.9
A123: B2 | B123: B2 BLANCO | C123: 5068 | D123: 5068 | E123: 60.26 | F123: =Tabla7[[#This Row],[METROS FISCAL]]*Tabla7[[#This Row],[PRECIO X METROS]] -> 305397.68
A124: B2 | B124: B2 GREY COLUMBA | C124: 76 | D124: 76 | E124: 70.91 | F124: =Tabla7[[#This Row],[METROS FISCAL]]*Tabla7[[#This Row],[PRECIO X METROS]] -> 5389.16
A125: B2 | B125: B2 LT GREY | C125: 294 | D125: 294 | E125: 70.91 | F125: =Tabla7[[#This Row],[METROS FISCAL]]*Tabla7[[#This Row],[PRECIO X METROS]] -> 20847.54
A126: B2 | B126: B2 PINK SKIN | C126: 138 | D126: 138 | E126: 70.91 | F126: =Tabla7[[#This Row],[METROS FISCAL]]*Tabla7[[#This Row],[PRECIO X METROS]] -> 9785.58
A127: B2 | B127: B2 WHITE AVORIO | C127: 287 | D127: 287 | E127: 70.91 | F127: =Tabla7[[#This Row],[METROS FISCAL]]*Tabla7[[#This Row],[PRECIO X METROS]] -> 20351.17
A128: Callicot | B128: CALLICOT AZURE LT | C128: 484 | D128: 484 | E128: 14.95 | F128: =Tabla7[[#This Row],[METROS FISCAL]]*Tabla7[[#This Row],[PRECIO X METROS]] -> 7235.8
A129: Callicot | B129: CALLICOT BEIGE ALMOND | C129: 75 | D129: 75 | E129: 14.95 | F129: =Tabla7[[#This Row],[METROS FISCAL]]*Tabla7[[#This Row],[PRECIO X METROS]] -> 1121.25
A130: Callicot | B130: CALLICOT BLANCO | C130: 6816 | D130: 6816 | E130: 11.32 | F130: =Tabla7[[#This Row],[METROS FISCAL]]*Tabla7[[#This Row],[PRECIO X METROS]] -> 77157.12
... A137: Callicot | B137: CALLICOT WHITE AVORIO | C137: 283 | D137: 283 | E137: 14.95 | F137: =Tabla7[[#This Row],[METROS FISCAL]]*Tabla7[[#This Row],[PRECIO X METROS]] -> 4230.85
A138: Interlook | B138: INTERLOCK TROPICAL BLANCO (COTTON JERSEY) | C138: 988.31 | E138: 118 | F138: =Tabla7[[#This Row],[METROS FISCAL]]*Tabla7[[#This Row],[PRECIO X METROS]] -> 116620.58
A139: Interlook | B139: INTERLOCK TROPICAL CAFE ESSPRESSO(COTTON JERSEY) | C139: 371.6 | E139: 130 | F139: =Tabla7[[#This Row],[METROS FISCAL]]*Tabla7[[#This Row],[PRECIO X METROS]] -> 48308
A140: Interlook | B140: INTERLOCK TROPICAL MARINO (COTTON JERSEY) | C140: 148 | E140: 125 | F140: =Tabla7[[#This Row],[METROS FISCAL]]*Tabla7[[#This Row],[PRECIO X METROS]] -> 18500
A141: Interlook | B141: INTERLOCK TROPICAL NEGRO (COTTON JERSEY) | C141: 106 | E141: 135 | F141: =Tabla7[[#This Row],[METROS FISCAL]]*Tabla7[[#This Row],[PRECIO X METROS]] -> 14310
A142: Interlook | B142: INTERLOCK TROPICAL STONE(COTTON JERSEY) | C142: 587.9 | E142: 130 | F142: =Tabla7[[#This Row],[METROS FISCAL]]*Tabla7[[#This Row],[PRECIO X METROS]] -> 76427
A143: Malla | B143: MALLA1 | C143: 30 | F143: =Tabla7[[#This Row],[METROS FISCAL]]*Tabla7[[#This Row],[PRECIO X METROS]] -> 0 | G143: China
A144: Malla | B144: MALLA2 | C144: 10 | F144: =Tabla7[[#This Row],[METROS FISCAL]]*Tabla7[[#This Row],[PRECIO X METROS]] -> 0 | G144: China
A145: Malla | B145: MALLA3 | C145: 15 | F145: =Tabla7[[#This Row],[METROS FISCAL]]*Tabla7[[#This Row],[PRECIO X METROS]] -> 0 | G145: China
A146: Malla | B146: MALLA4 | C146: 3 | F146: =Tabla7[[#This Row],[METROS FISCAL]]*Tabla7[[#This Row],[PRECIO X METROS]] -> 0 | G146: China
A147: Malla | B147: MALLA5 | C147: 2 | F147: =Tabla7[[#This Row],[METROS FISCAL]]*Tabla7[[#This Row],[PRECIO X METROS]] -> 0 | G147: China
A148: Malla | B148: MALLA6 | C148: 60 | F148: =Tabla7[[#This Row],[METROS FISCAL]]*Tabla7[[#This Row],[PRECIO X METROS]] -> 0 | G148: China
A149: Malla | B149: MALLA7 | C149: 42 | F149: =Tabla7[[#This Row],[METROS FISCAL]]*Tabla7[[#This Row],[PRECIO X METROS]] -> 0 | G149: China
A150: Malla | B150: MALLA8 | C150: 33 | F150: =Tabla7[[#This Row],[METROS FISCAL]]*Tabla7[[#This Row],[PRECIO X METROS]] -> 0 | G150: China
A151: Malla | B151: MALLA9 | C151: 11 | F151: =Tabla7[[#This Row],[METROS FISCAL]]*Tabla7[[#This Row],[PRECIO X METROS]] -> 0 | G151: China
A152: Malla | B152: MALLA10 / MESH NEGRO | C152: 27 | F152: =Tabla7[[#This Row],[METROS FISCAL]]*Tabla7[[#This Row],[PRECIO X METROS]] -> 0 | G152: China
A153: Popelina | B153: POPELINA BEIGE | C153: 12 | E153: 26.29 | F153: =Tabla7[[#This Row],[METROS FISCAL]]*Tabla7[[#This Row],[PRECIO X METROS]] -> 315.48 | G153: Precio de 2020
A154: Popelina | B154: POPELINA BLANCA | C154: 3 | E154: 26.29 | F154: =Tabla7[[#This Row],[METROS FISCAL]]*Tabla7[[#This Row],[PRECIO X METROS]] -> 78.87 | G154: Precio de 2020
A155: Popelina | B155: POPELINA MARINO | C155: 100 | E155: 26.29 | F155: =Tabla7[[#This Row],[METROS FISCAL]]*Tabla7[[#This Row],[PRECIO X METROS]] -> 2629 | G155: Precio de 2020
A156: Popelina | B156: POPELINA NEGRO | C156: 100 | E156: 26.29 | F156: =Tabla7[[#This Row],[METROS FISCAL]]*Tabla7[[#This Row],[PRECIO X METROS]] -> 2629 | G156: Precio de 2020
A157: Popelina | B157: POPELINA ROJA | C157: 6 | E157: 26.29 | F157: =Tabla7[[#This Row],[METROS FISCAL]]*Tabla7[[#This Row],[PRECIO X METROS]] -> 157.74 | G157: Precio de 2020
A158: Popelina | B158: POPELINA VERDE | C158: 120 | E158: 26.29 | F158: =Tabla7[[#This Row],[METROS FISCAL]]*Tabla7[[#This Row],[PRECIO X METROS]] -> 3154.8 | G158: Precio de 2020
A159: Popelina | B159: POPELINA VERDE AGUA | C159: 90 | E159: 26.29 | F159: =Tabla7[[#This Row],[METROS FISCAL]]*Tabla7[[#This Row],[PRECIO X METROS]] -> 2366.1 | G159: Precio de 2020
A160: Sarga | B160: GABARDINA BLANCA S/A | C160: 40 | E160: 54.25 | F160: =Tabla7[[#This Row],[METROS FISCAL]]*Tabla7[[#This Row],[PRECIO X METROS]] -> 2170
A161: Sarga | B161: GABARDINA ROJO C/A | C161: 200 | E161: 57.13 | F161: =Tabla7[[#This Row],[METROS FISCAL]]*Tabla7[[#This Row],[PRECIO X METROS]] -> 11426
A162: Sarga | B162: GABARDINA ROJO S/A | C162: 350 | E162: 54.25 | F162: =Tabla7[[#This Row],[METROS FISCAL]]*Tabla7[[#This Row],[PRECIO X METROS]] -> 18987.5
A163: Sarga | B163: GABARDINA ROSA C/A | C163: 200 | E163: 57.13 | F163: =Tabla7[[#This Row],[METROS FISCAL]]*Tabla7[[#This Row],[PRECIO X METROS]] -> 11426
A164: Sarga | B164: GABARDINA ROSA S/A | C164: 300 | E164: 54.25 | F164: =Tabla7[[#This Row],[METROS FISCAL]]*Tabla7[[#This Row],[PRECIO X METROS]] -> 16275
A165: Sarga | B165: GABARDINA VINO C/A | C165: 200 | E165: 57.13 | F165: =Tabla7[[#This Row],[METROS FISCAL]]*Tabla7[[#This Row],[PRECIO X METROS]] -> 11426
A166: Sarga | B166: GABARDINA VINO S/A | C166: 120 | E166: 54.25 | F166: =Tabla7[[#This Row],[METROS FISCAL]]*Tabla7[[#This Row],[PRECIO X METROS]] -> 6510
A167: Sarga | B167: MARÍA CRUDA | C167: 2 | E167: 43.17 | F167: =Tabla7[[#This Row],[METROS FISCAL]]*Tabla7[[#This Row],[PRECIO X METROS]] -> 86.34
...

Sheet TelaNoUtilizable
A1: CÓDIGO | B1: DESCRIPCIÓN | C1: METROS | D1: PRECIO X METROS | E1: TOTAL | F1: Obervaciones | G1: Fecha última compra localizada
A2: * | B2: Sintético Grasshopper / Nubuck | C2: =20*50 -> 1000 | E2: =D2*C2 -> 0 | F2: Daño por humedad / Desintegracion
A3: * | B3: Rayas verde / Acopol | C3: 40 | D3: 0 | E3: =D3*C3 -> 0 | F3: Con hongo | G3: 42402
A4: * | B4: Tela AE Gris | C4: 196 | E4: =D4*C4 -> 0 | F4: Mojado / Hongo
A5: * | B5: Tela AE Gris | C5: 118 | E5: =D5*C5 -> 0 | F5: Dañada por animales
A6: * | B6: Tela AE Gris | C6: 100 | E6: =D6*C6 -> 0 | F6: Dañada por animales
A7: * | B7: Tela AE Gris | C7: 50 | E7: =D7*C7 -> 0 | F7: Dañada por animales
A8: * | B8: Tela AE Gris | C8: 20 | E8: =D8*C8 -> 0 | F8: Dañada por animales
A9: * | B9: Sintético Azul Marino | C9: 10 | E9: =D9*C9 -> 0 | F9: Daño por humedad / Desintegracion
A10: * | B10: Sintético Azul Marino | C10: 50 | E10: =D10*C10 -> 0 | F10: Daño por humedad / Desintegracion
A11: * | B11: Sintético Azul Marino | C11: 50 | E11: =D11*C11 -> 0 | F11: Daño por humedad / Desintegracion
A12: * | B12: Sintético Azul Marino | C12: 30 | E12: =D12*C12 -> 0 | F12: Daño por humedad / Desintegracion
A13: * | B13: Twill Navy | C13: 10 | E13: =D13*C13 -> 0 | F13: Con hongo
A14: * | B14: Metallic Rose | C14: 10 | E14: =D14*C14 -> 0 | F14: Con hongo
A15: * | B15: Sintético Negro Pronanya | C15: 40 | E15: =D15*C15 -> 0 | F15: Desprendimiento de acabado
A16: * | B16: Sintético Negro | C16: 10 | E16: =D16*C16 -> 0 | F16: Daño por humedad / Desintegracion
A17: * | B17: Lona Negra | C17: 3 | D17: 0 | E17: =D17*C17 -> 0 | F17: Dañada por animales
A18: * | B18: Plix Off White | C18: 10 | D18: 0 | E18: =D18*C18 -> 0 | F18: Dañada por animales
A19: * | B19: Sintético Blanco | C19: 10 | E19: =D19*C19 -> 0 | F19: Daño por humedad / Desintegracion
C22: =SUM(C2:C21) -> 1757 | E22: =SUM(E2:E21) -> 0

Sheet Hulera
H1: Tipo de cambio | I1: 18.02 | J1: 46010 | K1: Banco de Mx
A2: Materiales | B2: NOMBRE SIMPLE | C2: CANTIDAD | D2: COSTO | E2: Unidad | F2: Importe | G2: OBSERVACIONES | H2: ÚLTIMA COMPRA | I2: PROVEEDOR | J2: Cost/dls o Pesos
A3: ANTIOXIDANTE DANOX 1076 | B3: Antioxidante | C3: 50 | D3: =+IF(Tabla1[[#This Row],[OBSERVACIONES]]="Dólares",Tabla1[[#This Row],[Cost/dls o Pesos]]*$I$1,Tabla1[[#This Row],[Cost/dls o Pesos]]) -> 171.19 | E3: Kg | F3: =+Tabla1[[#This Row],[CANTIDAD]]*Tabla1[[#This Row],[COSTO]] -> 8559.5 | G3: Dólares | H3: 45973 | I3: FATA | J3: 9.5
A4: ANTIOXIDANTE WINGSTAY | B4: Antioxidante | C4: 0 | D4: =+IF(Tabla1[[#This Row],[OBSERVACIONES]]="Dólares",Tabla1[[#This Row],[Cost/dls o Pesos]]*$I$1,Tabla1[[#This Row],[Cost/dls o Pesos]]) -> 10 | E4: Kg | F4: =+Tabla1[[#This Row],[CANTIDAD]]*Tabla1[[#This Row],[COSTO]] -> 0 | J4: 10
A5: CARBONATO DE CALCIO MICRONIZADO 1 | B5: Carbonato de calcio micronizado | C5: 0 | D5: =+IF(Tabla1[[#This Row],[OBSERVACIONES]]="Dólares",Tabla1[[#This Row],[Cost/dls o Pesos]]*$I$1,Tabla1[[#This Row],[Cost/dls o Pesos]]) -> 6 | E5: Kg | F5: =+Tabla1[[#This Row],[CANTIDAD]]*Tabla1[[#This Row],[COSTO]] -> 0 | J5: 6
A6: CARBONATO DE CALCIO PRECIPITAD | B6: Carbonato de calcio precipitado | C6: 400 | D6: =+IF(Tabla1[[#This Row],[OBSERVACIONES]]="Dólares",Tabla1[[#This Row],[Cost/dls o Pesos]]*$I$1,Tabla1[[#This Row],[Cost/dls o Pesos]]) -> 18.5 | E6: Kg | F6: =+Tabla1[[#This Row],[CANTIDAD]]*Tabla1[[#This Row],[COSTO]] -> 7400 | H6: 45973 | I6: FATA | J6: 18.5
A7: MIXLAND S80 GA F500 AZUFRE Bombones | B7: AZUFRE | C7: 50 | D7: =+IF(Tabla1[[#This Row],[OBSERVACIONES]]="Dólares",Tabla1[[#This Row],[Cost/dls o Pesos]]*$I$1,Tabla1[[#This Row],[Cost/dls o Pesos]]) -> 29.0122 | E7: Kg | F7: =+Tabla1[[#This Row],[CANTIDAD]]*Tabla1[[#This Row],[COSTO]] -> 1450.61 | G7: Dólares | H7: 45980 | I7: QUIMIPOL | J7: 1.61
A8: MIXLAND NEW GEN TMTD 80G Bombones | B8: TMT/ Bombones | C8: 80 | D8: =+IF(Tabla1[[#This Row],[OBSERVACIONES]]="Dólares",Tabla1[[#This Row],[Cost/dls o Pesos]]*$I$1,Tabla1[[#This Row],[Cost/dls o Pesos]]) -> 111.0032 | E8: Kg | F8: =+Tabla1[[#This Row],[CANTIDAD]]*Tabla1[[#This Row],[COSTO]] -> 8880.256 | G8: Dólares | H8: 45979 | I8: SUMINISTRO | J8: 6.16
A9: TMTD Polvo | B9: TMT/ Polvo | C9: 0 | D9: =+IF(Tabla1[[#This Row],[OBSERVACIONES]]="Dólares",Tabla1[[#This Row],[Cost/dls o Pesos]]*$I$1,Tabla1[[#This Row],[Cost/dls o Pesos]]) -> 99.11 | E9: Kg | F9: =+Tabla1[[#This Row],[CANTIDAD]]*Tabla1[[#This Row],[COSTO]] -> 0 | G9: Dólares | J9: 5.5
A10: BIOXIDO DE TITANIO R 103 | B10: Bióxido de titanio R-103 | C10: 75 | D10: =+IF(Tabla1[[#This Row],[OBSERVACIONES]]="Dólares",Tabla1[[#This Row],[Cost/dls o Pesos]]*$I$1,Tabla1[[#This Row],[Cost/dls o Pesos]]) -> 68.9 | E10: Kg | F10: =+Tabla1[[#This Row],[CANTIDAD]]*Tabla1[[#This Row],[COSTO]] -> 5167.5 | H10: 45981 | I10: NASEDA | J10: 68.9
A11: AGENTE ANTI UV | B11: ANTI UV | C11: 13 | D11: =+IF(Tabla1[[#This Row],[OBSERVACIONES]]="Dólares",Tabla1[[#This Row],[Cost/dls o Pesos]]*$I$1,Tabla1[[#This Row],[Cost/dls o Pesos]]) -> 390 | E11: Kg | F11: =+Tabla1[[#This Row],[CANTIDAD]]*Tabla1[[#This Row],[COSTO]] -> 5070 | H11: 45791 | I11: CREPÉ | J11: 390
A12: AC EST Q1012 ESCAMAS | B12: Ácido estéarico Q1012 Escamas | C12: 50 | D12: =+IF(Tabla1[[#This Row],[OBSERVACIONES]]="Dólares",Tabla1[[#This Row],[Cost/dls o Pesos]]*$I$1,Tabla1[[#This Row],[Cost/dls o Pesos]]) -> 34.9588 | E12: Kg | F12: =+Tabla1[[#This Row],[CANTIDAD]]*Tabla1[[#This Row],[COSTO]] -> 1747.94 | G12: Dólares | H12: 45980 | I12: QUIMIPOL | J12: 1.94
A13: ACELERANTE M.B.T.S. POLVO (SOVCHEM MBTS POLVO) | B13: MBTS/ Polvo | C13: 0 | D13: =+IF(Tabla1[[#This Row],[OBSERVACIONES]]="Dólares",Tabla1[[#This Row],[Cost/dls o Pesos]]*$I$1,Tabla1[[#This Row],[Cost/dls o Pesos]]) -> 95.506 | E13: Kg | F13: =+Tabla1[[#This Row],[CANTIDAD]]*Tabla1[[#This Row],[COSTO]] -> 0 | G13: Dólares | J13: 5.3
A14: MIXLAND NEW GEN MBTS 75G Bombones | B14: MBTS/ Bombones | C14: 20 | D14: =+IF(Tabla1[[#This Row],[OBSERVACIONES]]="Dólares",Tabla1[[#This Row],[Cost/dls o Pesos]]*$I$1,Tabla1[[#This Row],[Cost/dls o Pesos]]) -> 127.942 | E14: Kg | F14: =+Tabla1[[#This Row],[CANTIDAD]]*Tabla1[[#This Row],[COSTO]] -> 2558.84 | G14: Dólares | H14: 45972 | I14: SUMINISTRO | J14: 7.1
A15: A032 MASTER CREPE NEGRO | C15: 40 | D15: =+IF(Tabla1[[#This Row],[OBSERVACIONES]]="Dólares",Tabla1[[#This Row],[Cost/dls o Pesos]]*$I$1,Tabla1[[#This Row],[Cost/dls o Pesos]]) -> 68.78 | E15: Kg | F15: =+Tabla1[[#This Row],[CANTIDAD]]*Tabla1[[#This Row],[COSTO]] -> 2751.2 | H15: 45947 | I15: VICSOL | J15: 68.78
A16: ACEITE NAFTENICO 100 | B16: ACEITE NAFTENICO 100 | C16: =180*2 -> 360 | D16: =+IF(Tabla1[[#This Row],[OBSERVACIONES]]="Dólares",Tabla1[[#This Row],[Cost/dls o Pesos]]*$I$1,Tabla1[[#This Row],[Cost/dls o Pesos]]) -> 26.5 | E16: Kg | F16: =+Tabla1[[#This Row],[CANTIDAD]]*Tabla1[[#This Row],[COSTO]] -> 9540 | H16: 45980 | I16: CREPÉ | J16: 26.5
A17: AZUFRE EXTRAFINO | B17: Azufre Extrafino | C17: 5 | D17: =+IF(Tabla1[[#This Row],[OBSERVACIONES]]="Dólares",Tabla1[[#This Row],[Cost/dls o Pesos]]*$I$1,Tabla1[[#This Row],[Cost/dls o Pesos]]) -> 24.5 | E17: Kg | F17: =+Tabla1[[#This Row],[CANTIDAD]]*Tabla1[[#This Row],[COSTO]] -> 122.5 | G17: Compra noviembre 2022 | H17: - | I17: - | J17: 24.5
A18: AZUL ULTRA MAR 463 | B18: AZUL ULTRA MAR | C18: 30 | D18: =+IF(Tabla1[[#This Row],[OBSERVACIONES]]="Dólares",Tabla1[[#This Row],[Cost/dls o Pesos]]*$I$1,Tabla1[[#This Row],[Cost/dls o Pesos]]) -> 124.46 | E18: Kg | F18: =+Tabla1[[#This Row],[CANTIDAD]]*Tabla1[[#This Row],[COSTO]] -> 3733.8 | H18: 45771 | I18: NASEDA | J18: 124.46
A19: BAYFERROX CAFE 686 | B19: BAYFERROX CAFE 686 | C19: 7 | D19: =+IF(Tabla1[[#This Row],[OBSERVACIONES]]="Dólares",Tabla1[[#This Row],[Cost/dls o Pesos]]*$I$1,Tabla1[[#This Row],[Cost/dls o Pesos]]) -> 48.86 | E19: Kg | F19: =+Tabla1[[#This Row],[CANTIDAD]]*Tabla1[[#This Row],[COSTO]] -> 342.02 | G19: Última compra localizada 14.06.2021 | H19: - | I19: - | J19: 48.86
A20: BREA CLARA W | B20: Brea Clara | C20: 10 | D20: =+IF(Tabla1[[#This Row],[OBSERVACIONES]]="Dólares",Tabla1[[#This Row],[Cost/dls o Pesos]]*$I$1,Tabla1[[#This Row],[Cost/dls o Pesos]]) -> 48 | E20: Kg | F20: =+Tabla1[[#This Row],[CANTIDAD]]*Tabla1[[#This Row],[COSTO]] -> 480 | H20: 45973 | I20: FATA | J20: 48
A21: CERA *56 | B21: CERA | C21: 25 | D21: =+IF(Tabla1[[#This Row],[OBSERVACIONES]]="Dólares",Tabla1[[#This Row],[Cost/dls o Pesos]]*$I$1,Tabla1[[#This Row],[Cost/dls o Pesos]]) -> 46 | E21: Kg | F21: =+Tabla1[[#This Row],[CANTIDAD]]*Tabla1[[#This Row],[COSTO]] -> 1150 | H21: 45972 | I21: CREPÉ | J21: 46
A22: ESTEARATO DE ZINC T(PROQUIESTAR ZN)(PETRAC ZN) | B22: ESTEREATO DE ZINC | C22: 20 | D22: =+IF(Tabla1[[#This Row],[OBSERVACIONES]]="Dólares",Tabla1[[#This Row],[Cost/dls o Pesos]]*$I$1,Tabla1[[#This Row],[Cost/dls o Pesos]]) -> 75.5038 | E22: Kg | F22: =+Tabla1[[#This Row],[CANTIDAD]]*Tabla1[[#This Row],[COSTO]] -> 1510.076 | G22: Dólares | H22: 45966 | I22: VICSOL | J22: 4.19
A23: HULE EMULPRENE E260 CONCHITAS | B23: HULE EMULPRENE E260 CONCHITAS | C23: 10 | D23: =+IF(Tabla1[[#This Row],[OBSERVACIONES]]="Dólares",Tabla1[[#This Row],[Cost/dls o Pesos]]*$I$1,Tabla1[[#This Row],[Cost/dls o Pesos]]) -> 77.486 | E23: Kg | F23: =+Tabla1[[#This Row],[CANTIDAD]]*Tabla1[[#This Row],[COSTO]] -> 774.86 | G23: Dólares | H23: 45868 | I23: VICSOL | J23: 4.3
A24: IPISA SILANO 69 | B24: IPISA SILANO 69 | C24: 20 | D24: =+IF(Tabla1[[#This Row],[OBSERVACIONES]]="Dólares",Tabla1[[#This Row],[Cost/dls o Pesos]]*$I$1,Tabla1[[#This Row],[Cost/dls o Pesos]]) -> 78.5 | E24: Litros | F24: =+Tabla1[[#This Row],[CANTIDAD]]*Tabla1[[#This Row],[COSTO]] -> 1570 | G24: Última compra localizada 22.06.22 | H24: - | I24: - | J24: 78.5
A25: MICROTARD A | B25: MICROTARD A | C25: 25 | D25: =+IF(Tabla1[[#This Row],[OBSERVACIONES]]="Dólares",Tabla1[[#This Row],[Cost/dls o Pesos]]*$I$1,Tabla1[[#This Row],[Cost/dls o Pesos]]) -> 87.397 | E25: Kg | F25: =+Tabla1[[#This Row],[CANTIDAD]]*Tabla1[[#This Row],[COSTO]] -> 2184.925 | G25: Dólares | H25: 45965 | I25: SUMINISTRO | J25: 4.85
A26: MONO COAT E 304 | B26: MONO COAT E 304 | C26: =14.88*2 -> 29.76 | D26: =+IF(Tabla1[[#This Row],[OBSERVACIONES]]="Dólares",Tabla1[[#This Row],[Cost/dls o Pesos]]*$I$1,Tabla1[[#This Row],[Cost/dls o Pesos]]) -> 522.58 | E26: Kg | F26: =+Tabla1[[#This Row],[CANTIDAD]]*Tabla1[[#This Row],[COSTO]] -> 15551.981 | G26: Dólares | H26: 45959 | I26: FATA | J26: 29
A27: NBR 6850 LG HULE | B27: NBR 6850 LG HULE | C27: 0 | D27: =+IF(Tabla1[[#This Row],[OBSERVACIONES]]="Dólares",Tabla1[[#This Row],[Cost/dls o Pesos]]*$I$1,Tabla1[[#This Row],[Cost/dls o Pesos]]) -> 84.05 | E27: Kg | F27: =+Tabla1[[#This Row],[CANTIDAD]]*Tabla1[[#This Row],[COSTO]] -> 0 | J27: 84.05
A28: OXIDO DE ZINC TRANSPARENTE COREANO | B28: OXIDO DE ZINC TRANSPARENTE COREANO | C28: 100 | D28: =+IF(Tabla1[[#This Row],[OBSERVACIONES]]="Dólares",Tabla1[[#This Row],[Cost/dls o Pesos]]*$I$1,Tabla1[[#This Row],[Cost/dls o Pesos]]) -> 51.357 | E28: Kg | F28: =+Tabla1[[#This Row],[CANTIDAD]]*Tabla1[[#This Row],[COSTO]] -> 5135.7 | G28: Dólares | H28: 45966 | I28: VICSOL | J28: 2.85
A29: PLURACOL E-4000 | B29: PEG-4000 | C29: 100 | D29: =+IF(Tabla1[[#This Row],[OBSERVACIONES]]="Dólares",Tabla1[[#This Row],[Cost/dls o Pesos]]*$I$1,Tabla1[[#This Row],[Cost/dls o Pesos]]) -> 40 | E29: Kg | F29: =+Tabla1[[#This Row],[CANTIDAD]]*Tabla1[[#This Row],[COSTO]] -> 4000 | H29: 45980 | I29: CREPÉ | J29: 40
A30: SILICA HULERA SP-200 GRANULADO | B30: Sílica Granulada | C30: 1900 | D30: =+IF(Tabla1[[#This Row],[OBSERVACIONES]]="Dólares",Tabla1[[#This Row],[Cost/dls o Pesos]]*$I$1,Tabla1[[#This Row],[Cost/dls o Pesos]]) -> 18.02 | E30: Kg | F30: =+Tabla1[[#This Row],[CANTIDAD]]*Tabla1[[#This Row],[COSTO]] -> 34238 | G30: Dólares | H30: 45992 | I30: KAUCHO QUIMICO | J30: 1
A31: STRUKTOL A-60 (PESTIZANTE) | B31: STRUKTOL A-60 (PESTIZANTE) | C31: 20 | D31: =+IF(Tabla1[[#This Row],[OBSERVACIONES]]="Dólares",Tabla1[[#This Row],[Cost/dls o Pesos]]*$I$1,Tabla1[[#This Row],[Cost/dls o Pesos]]) -> 14.58 | E31: Kg | F31: =+Tabla1[[#This Row],[CANTIDAD]]*Tabla1[[#This Row],[COSTO]] -> 291.6 | G31: Última compra localizada 26.11.2020 | H31: - | I31: - | J31: 14.58
A32: RESINA FENÓLICA | B32: RESINA | C32: 25 | D32: =+IF(Tabla1[[#This Row],[OBSERVACIONES]]="Dólares",Tabla1[[#This Row],[Cost/dls o Pesos]]*$I$1,Tabla1[[#This Row],[Cost/dls o Pesos]]) -> 53.159 | E32: Kg | F32: =+Tabla1[[#This Row],[CANTIDAD]]*Tabla1[[#This Row],[COSTO]] -> 1328.975 | G32: Dólares | H32: 45965 | I32: SUMINISTRO | J32: 2.95
A33: SÍLICA MICROPERLA | B33: SÍLICA MICROPERLA | C33: 40 | D33: =+IF(Tabla1[[#This Row],[OBSERVACIONES]]="Dólares",Tabla1[[#This Row],[Cost/dls o Pesos]]*$I$1,Tabla1[[#This Row],[Cost/dls o Pesos]]) -> 28.832 | E33: Kg | F33: =+Tabla1[[#This Row],[CANTIDAD]]*Tabla1[[#This Row],[COSTO]] -> 1153.28 | G33: Dólares | H33: 45966 | I33: VICSOL | J33: 1.6
A34: PIGMENTO ROJO R2 | B34: PIGMENTO ROJO R2 | C34: 30 | D34: =+IF(Tabla1[[#This Row],[OBSERVACIONES]]="Dólares",Tabla1[[#This Row],[Cost/dls o Pesos]]*$I$1,Tabla1[[#This Row],[Cost/dls o Pesos]]) -> 494 | E34: Kg | F34: =+Tabla1[[#This Row],[CANTIDAD]]*Tabla1[[#This Row],[COSTO]] -> 14820 | G34: No hay compras en sistema de éste material | H34: - | I34: - | J34: 494
A35: PIGMENTO NARANJA H2G2 | B35: PIGMENTO NARANJA H2G2 | C35: 50 | D35: =+IF(Tabla1[[#This Row],[OBSERVACIONES]]="Dólares",Tabla1[[#This Row],[Cost/dls o Pesos]]*$I$1,Tabla1[[#This Row],[Cost/dls o Pesos]]) -> 1055 | E35: Kg | F35: =+Tabla1[[#This Row],[CANTIDAD]]*Tabla1[[#This Row],[COSTO]] -> 52750 | H35: - | I35: - | J35: 1055
A36: PIGMENTO ROJO ÓXIDO | B36: PIGMENTO ROJO ÓXIDO | C36: 20 | D36: =+IF(Tabla1[[#This Row],[OBSERVACIONES]]="Dólares",Tabla1[[#This Row],[Cost/dls o Pesos]]*$I$1,Tabla1[[#This Row],[Cost/dls o Pesos]]) -> 145 | E36: Kg | F36: =+Tabla1[[#This Row],[CANTIDAD]]*Tabla1[[#This Row],[COSTO]] -> 2900 | H36: - | I36: - | J36: 145
A37: PIGMENTO AZUL 7012 | B37: PIGMENTO AZUL 7012 | C37: 4 | D37: =+IF(Tabla1[[#This Row],[OBSERVACIONES]]="Dólares",Tabla1[[#This Row],[Cost/dls o Pesos]]*$I$1,Tabla1[[#This Row],[Cost/dls o Pesos]]) -> 514 | E37: Kg | F37: =+Tabla1[[#This Row],[CANTIDAD]]*Tabla1[[#This Row],[COSTO]] -> 2056 | H37: - | I37: - | J37: 514
A38: PIGMENTO AMARILLO 3GP | B38: AMARILLO 3GP | C38: 10 | D38: =+IF(Tabla1[[#This Row],[OBSERVACIONES]]="Dólares",Tabla1[[#This Row],[Cost/dls o Pesos]]*$I$1,Tabla1[[#This Row],[Cost/dls o Pesos]]) -> 944 | E38: Kg | F38: =+Tabla1[[#This Row],[CANTIDAD]]*Tabla1[[#This Row],[COSTO]] -> 9440 | H38: 45840 | I38: SUMIPLAST | J38: 944
A39: PIGMENTO AMARILLO ÓXIDO | B39: PIGMENTO AMARILLO ÓXIDO | C39: 10 | D39: =+IF(Tabla1[[#This Row],[OBSERVACIONES]]="Dólares",Tabla1[[#This Row],[Cost/dls o Pesos]]*$I$1,Tabla1[[#This Row],[Cost/dls o Pesos]]) -> 944 | E39: Kg | F39: =+Tabla1[[#This Row],[CANTIDAD]]*Tabla1[[#This Row],[COSTO]] -> 9440 | G39: Sin precio, se toma valor de amarillo 3GP | H39: - | I39: - | J39: 944
A40: DIATILENGLICOL | B40: DIETILENGLICOL | C40: 80 | D40: =+IF(Tabla1[[#This Row],[OBSERVACIONES]]="Dólares",Tabla1[[#This Row],[Cost/dls o Pesos]]*$I$1,Tabla1[[#This Row],[Cost/dls o Pesos]]) -> 49.56 | E40: Litros | F40: =+Tabla1[[#This Row],[CANTIDAD]]*Tabla1[[#This Row],[COSTO]] -> 3964.8 | G40: Última compra localizada 21.07.2021 | H40: - | I40: - | J40: 49.56
A41: ÓXIDO DE ZINC ACTIVO | B41: ÓXIDO DE ZINC ACTIVO | C41: 100 | D41: =+IF(Tabla1[[#This Row],[OBSERVACIONES]]="Dólares",Tabla1[[#This Row],[Cost/dls o Pesos]]*$I$1,Tabla1[[#This Row],[Cost/dls o Pesos]]) -> 73.6 | E41: Kg | F41: =+Tabla1[[#This Row],[CANTIDAD]]*Tabla1[[#This Row],[COSTO]] -> 7360 | H41: 45981 | I41: NASEDA | J41: 73.6
A42: DESMOLDANTE A-16 | B42: DESMOLDANTE SPRAY | C42: =2*12 -> 24 | D42: =+IF(Tabla1[[#This Row],[OBSERVACIONES]]="Dólares",Tabla1[[#This Row],[Cost/dls o Pesos]]*$I$1,Tabla1[[#This Row],[Cost/dls o Pesos]]) -> 42.5 | E42: Pza | F42: =+Tabla1[[#This Row],[CANTIDAD]]*Tabla1[[#This Row],[COSTO]] -> 1020 | H42: 45972 | I42: NASEDA | J42: 42.5
A43: SAL PELLETS AQUATROL 20KGS | B43: SUAVIZADOR DE AGUA | C43: 60 | D43: =+IF(Tabla1[[#This Row],[OBSERVACIONES]]="Dólares",Tabla1[[#This Row],[Cost/dls o Pesos]]*$I$1,Tabla1[[#This Row],[Cost/dls o Pesos]]) -> 10.925 | E43: Kg | F43: =+Tabla1[[#This Row],[CANTIDAD]]*Tabla1[[#This Row],[COSTO]] -> 655.5 | H43: 46005 | I43: MORSAWT | J43: 10.925
A44: HULE 3L | B44: HULE 3L | C44: 315 | D44: =+IF(Tabla1[[#This Row],[OBSERVACIONES]]="Dólares",Tabla1[[#This Row],[Cost/dls o Pesos]]*$I$1,Tabla1[[#This Row],[Cost/dls o Pesos]]) -> 55 | E44: Kg | F44: =+Tabla1[[#This Row],[CANTIDAD]]*Tabla1[[#This Row],[COSTO]] -> 17325 | J44: 55
A45: HULE 1502 LÍNEA | B45: HULE 1502 | C45: 500 | D45: =+IF(Tabla1[[#This Row],[OBSERVACIONES]]="Dólares",Tabla1[[#This Row],[Cost/dls o Pesos]]*$I$1,Tabla1[[#This Row],[Cost/dls o Pesos]]) -> 44 | E45: Kg | F45: =+Tabla1[[#This Row],[CANTIDAD]]*Tabla1[[#This Row],[COSTO]] -> 22000 | G45: KER | J45: 44 | M45: 37 | N45: 62
A46: HULE 1502 PRIMERA OSCURO | B46: HULE 1502 OSCURO | C46: 0 | D46: =+IF(Tabla1[[#This Row],[OBSERVACIONES]]="Dólares",Tabla1[[#This Row],[Cost/dls o Pesos]]*$I$1,Tabla1[[#This Row],[Cost/dls o Pesos]]) -> 62 | E46: Kg | F46: =+Tabla1[[#This Row],[CANTIDAD]]*Tabla1[[#This Row],[COSTO]] -> 0 | G46: X | J46: 62
A47: HULE 1502 ECO | B47: HULE 1502 ECO | C47: 0 | D47: =+IF(Tabla1[[#This Row],[OBSERVACIONES]]="Dólares",Tabla1[[#This Row],[Cost/dls o Pesos]]*$I$1,Tabla1[[#This Row],[Cost/dls o Pesos]]) -> 45 | E47: Kg | F47: =+Tabla1[[#This Row],[CANTIDAD]]*Tabla1[[#This Row],[COSTO]] -> 0 | G47: X | J47: 45
A48: HULE STR20 BR | B48: HULE HM20 | C48: 90 | D48: =+IF(Tabla1[[#This Row],[OBSERVACIONES]]="Dólares",Tabla1[[#This Row],[Cost/dls o Pesos]]*$I$1,Tabla1[[#This Row],[Cost/dls o Pesos]]) -> 60 | E48: Kg | F48: =+Tabla1[[#This Row],[CANTIDAD]]*Tabla1[[#This Row],[COSTO]] -> 5400 | G48: Última compra localizada 26.09.2022 | J48: 60
A49: PBD | B49: HULE PBD | C49: 0 | D49: =+IF(Tabla1[[#This Row],[OBSERVACIONES]]="Dólares",Tabla1[[#This Row],[Cost/dls o Pesos]]*$I$1,Tabla1[[#This Row],[Cost/dls o Pesos]]) -> 40 | E49: Kg | F49: =+Tabla1[[#This Row],[CANTIDAD]]*Tabla1[[#This Row],[COSTO]] -> 0 | G49: ALTO SIS | J49: 40
A50: HULE QUESO | B50: HULE QUESO | C50: 0 | D50: =+IF(Tabla1[[#This Row],[OBSERVACIONES]]="Dólares",Tabla1[[#This Row],[Cost/dls o Pesos]]*$I$1,Tabla1[[#This Row],[Cost/dls o Pesos]]) -> 49 | E50: kG | F50: =+Tabla1[[#This Row],[CANTIDAD]]*Tabla1[[#This Row],[COSTO]] -> 0 | G50: No tengo costo | J50: 49
F52: =SUM(F3:F51) -> 275824.86
D55: Material en movimiento | F55: =F52-F56 -> 199063.94
D56: Material inactivo | F56: =F17+F19+F24+F31+F34+F35+F36+F40 -> 76760.92

Sheet carga hule
A1: MATERIAL | B1: COLOR | C1: CANTIDAD | D1: Comentarios | E1: PESO X ROLLO (KG) | F1: 19/12/2025 | G1: OBS | H1: Precio | I1: Total
A2: CALZADORES | C2: =ROLLOS[[#This Row],[19/12/2025]]*ROLLOS[[#This Row],[PESO X ROLLO (KG)]] -> 180 | D2: Se realiza en molino | E2: 90 | F2: 2 | H2: 36.1 | I2: =+ROLLOS[[#This Row],[Precio]]*ROLLOS[[#This Row],[CANTIDAD]] -> 6498
A3: PASTA MARCA | C3: =ROLLOS[[#This Row],[19/12/2025]]*ROLLOS[[#This Row],[PESO X ROLLO (KG)]] -> 180 | E3: 90 | F3: 2 | H3: 39.8 | I3: =+ROLLOS[[#This Row],[Precio]]*ROLLOS[[#This Row],[CANTIDAD]] -> 7164
A4: PASTA PARA VIVOS | C4: =ROLLOS[[#This Row],[19/12/2025]]*ROLLOS[[#This Row],[PESO X ROLLO (KG)]] -> 180 | D4: 1 por color (negro, rojo, azul rey y natural) | E4: 60 | F4: 3 | G4: gum, suela calandreada se hace a 60 K, en molino abierto | H4: 39.8 | I4: =+ROLLOS[[#This Row],[Precio]]*ROLLOS[[#This Row],[CANTIDAD]] -> 7164
A5: PASTA SUELA | B5: COLORES | C5: =ROLLOS[[#This Row],[19/12/2025]]*ROLLOS[[#This Row],[PESO X ROLLO (KG)]] -> 630 | D5: Pasta de base | E5: 90 | F5: 7 | H5: 42.9 | I5: =+ROLLOS[[#This Row],[Precio]]*ROLLOS[[#This Row],[CANTIDAD]] -> 27027
A6: PASTA SUELA | B6: BCO LACOSTE | C6: =ROLLOS[[#This Row],[19/12/2025]]*ROLLOS[[#This Row],[PESO X ROLLO (KG)]] -> 360 | D6: Dependiendo el pedido | E6: 90 | F6: 4 | H6: 42.9 | I6: =+ROLLOS[[#This Row],[Precio]]*ROLLOS[[#This Row],[CANTIDAD]] -> 15444
A7: PASTA SUELA | B7: BCO LACOSTE / NUEVO | D7: Dependiendo el pedido | E7: 90 | F7: 0 | I7: =+ROLLOS[[#This Row],[Precio]]*ROLLOS[[#This Row],[CANTIDAD]] -> 0
A8: PASTA SUELA | B8: GUM | D8: Dependiendo el pedido | E8: 90 | F8: 0 | I8: =+ROLLOS[[#This Row],[Precio]]*ROLLOS[[#This Row],[CANTIDAD]] -> 0
A9: PASTA SUELA | B9: NEGRA SKECHER | D9: Revisar para usar en pastas actuales | E9: 90 | F9: 0 | I9: =+ROLLOS[[#This Row],[Precio]]*ROLLOS[[#This Row],[CANTIDAD]] -> 0
A10: PEGAMENTO | B10: BLANCO | D10: Mezclar con pegamento ámbar | F10: 0 | I10: =+ROLLOS[[#This Row],[Precio]]*ROLLOS[[#This Row],[CANTIDAD]] -> 0
A11: PEGAMENTO | B11: Ámbar | C11: =ROLLOS[[#This Row],[19/12/2025]]*ROLLOS[[#This Row],[PESO X ROLLO (KG)]] -> 0 | D11: Revisar inventario | F11: 0.5 | H11: 49.5 | I11: =+ROLLOS[[#This Row],[Precio]]*ROLLOS[[#This Row],[CANTIDAD]] -> 0
A12: RELLENO | B12: AZUL | D12: Inventarios mayores a 1, revisar pedidos | E12: 90 | F12: 0 | I12: =+ROLLOS[[#This Row],[Precio]]*ROLLOS[[#This Row],[CANTIDAD]] -> 0
A13: TIRA | B13: BCO COLLEC | C13: =ROLLOS[[#This Row],[19/12/2025]]*ROLLOS[[#This Row],[PESO X ROLLO (KG)]] -> 810 | E13: 90 | F13: 9 | H13: 39.8 | I13: =+ROLLOS[[#This Row],[Precio]]*ROLLOS[[#This Row],[CANTIDAD]] -> 32238
A14: TIRA | B14: KITS | F14: 0 | I14: =+ROLLOS[[#This Row],[Precio]]*ROLLOS[[#This Row],[CANTIDAD]] -> 0
A15: TIRA | B15: LACOSTE | D15: Dependiendo pedido Se utilizarán 35 rollos | E15: 90 | F15: 0 | I15: =+ROLLOS[[#This Row],[Precio]]*ROLLOS[[#This Row],[CANTIDAD]] -> 0
A16: TIRA | B16: PEYLES | C16: =ROLLOS[[#This Row],[19/12/2025]]*ROLLOS[[#This Row],[PESO X ROLLO (KG)]] -> 90 | D16: DC, POLO, NEXT | E16: 90 | F16: 1 | H16: 39.8 | I16: =+ROLLOS[[#This Row],[Precio]]*ROLLOS[[#This Row],[CANTIDAD]] -> 3582
A17: TIRA | B17: GUM | D17: Sobre pedido DC | E17: 60 | F17: 0 | G17: molino abierto | I17: =+ROLLOS[[#This Row],[Precio]]*ROLLOS[[#This Row],[CANTIDAD]] -> 0
A18: TIRA | B18: PERLA | C18: =ROLLOS[[#This Row],[19/12/2025]]*ROLLOS[[#This Row],[PESO X ROLLO (KG)]] -> 90 | D18: Sobre pedido (Revisar marcas) | E18: 90 | F18: 1 | H18: 39.8 | I18: =+ROLLOS[[#This Row],[Precio]]*ROLLOS[[#This Row],[CANTIDAD]] -> 3582
A19: TIRA | B19: NEGRA | C19: =ROLLOS[[#This Row],[19/12/2025]]*ROLLOS[[#This Row],[PESO X ROLLO (KG)]] -> 990 | E19: 90 | F19: 11 | H19: 38.8 | I19: =+ROLLOS[[#This Row],[Precio]]*ROLLOS[[#This Row],[CANTIDAD]] -> 38412
A20: TIRA | B20: SUPERGA | D20: Sobre pedido | E20: 90 | F20: 0 | I20: =+ROLLOS[[#This Row],[Precio]]*ROLLOS[[#This Row],[CANTIDAD]] -> 0
A21: TIRA | B21: NARANJA | D21: Sobre pedido | E21: 90 | F21: 0 | I21: =+ROLLOS[[#This Row],[Precio]]*ROLLOS[[#This Row],[CANTIDAD]] -> 0
A22: TIRA | B22: ROJA | D22: Sobre pedido | E22: 90 | F22: 0 | I22: =+ROLLOS[[#This Row],[Precio]]*ROLLOS[[#This Row],[CANTIDAD]] -> 0
A23: TIRA | B23: VINO | D23: Sobre pedido | E23: 90 | F23: 0 | I23: =+ROLLOS[[#This Row],[Precio]]*ROLLOS[[#This Row],[CANTIDAD]] -> 0
A24: TIRA | B24: DOVE | D24: Sobre pedido | E24: 90 | F24: 0 | I24: =+ROLLOS[[#This Row],[Precio]]*ROLLOS[[#This Row],[CANTIDAD]] -> 0
A25: TIRA | B25: GRIS RATA | D25: Sobre pedido | E25: 90 | F25: 0 | I25: =+ROLLOS[[#This Row],[Precio]]*ROLLOS[[#This Row],[CANTIDAD]] -> 0
A26: TIRA | B26: GRIS CLARO | D26: Sobre pedido | E26: 90 | F26: 0 | I26: =+ROLLOS[[#This Row],[Precio]]*ROLLOS[[#This Row],[CANTIDAD]] -> 0
A27: TIRA | B27: AMBAR NORMAL | D27: Sobre pedido | E27: 90 | F27: 0 | I27: =+ROLLOS[[#This Row],[Precio]]*ROLLOS[[#This Row],[CANTIDAD]] -> 0
A28: TIRA | B28: AMARILLA | D28: Sobre pedido | E28: 90 | F28: 0 | I28: =+ROLLOS[[#This Row],[Precio]]*ROLLOS[[#This Row],[CANTIDAD]] -> 0
A29: TIRA | B29: NATURAL | D29: Básica para muestras | E29: 90 | F29: 0 | I29: =+ROLLOS[[#This Row],[Precio]]*ROLLOS[[#This Row],[CANTIDAD]] -> 0
A30: TIRA | B30: AZUL REY | D30: Sobre pedido | E30: 90 | F30: 0 | I30: =+ROLLOS[[#This Row],[Precio]]*ROLLOS[[#This Row],[CANTIDAD]] -> 0
A31: SUELA | B31: CALANDREADA NAUTICA | C31: =ROLLOS[[#This Row],[19/12/2025]]*ROLLOS[[#This Row],[PESO X ROLLO (KG)]] -> 30 | D31: Náutica | E31: 60 | F31: 0.5 | H31: 51.5 | I31: =+ROLLOS[[#This Row],[Precio]]*ROLLOS[[#This Row],[CANTIDAD]] -> 1545
C32: =SUBTOTAL(109,ROLLOS[CANTIDAD]) -> 3540 | E32: =SUBTOTAL(109,ROLLOS[PESO X ROLLO (KG)]) -> 2340 | I32: =SUBTOTAL(109,ROLLOS[Total]) -> 142656
C34: =SUM(C33:C33) -> 0

Sheet Suela Mov
A1: INVENTARIO DE SUELA
A2: ESTILO | B2: COLOR | C2: TALLA | D2: CANTIDAD | E2: PARES/NONES | F2: PRECIO | G2: TOTAL
A3: Dany | B3: Negro | C3: Varias | D3: =10+10+10+10+35+4+15+10+8+4+5+8 -> 129 | E3: Pares | F3: 12.69 | G3: =+Tabla11312[[#This Row],[PRECIO]]*Tabla11312[[#This Row],[CANTIDAD]] -> 1637.01
A4: Panal | B4: Negro | C4: Varias | D4: =30+40+40+40+40+40+40+40+40+45+40 -> 435 | E4: Pares | F4: 15.11 | G4: =+Tabla11312[[#This Row],[PRECIO]]*Tabla11312[[#This Row],[CANTIDAD]] -> 6572.85
A5: Lacoste | B5: Blanco viejo | C5: Varias | D5: =25+32+45+90 -> 192 | E5: Pares | F5: 15.11 | G5: =+Tabla11312[[#This Row],[PRECIO]]*Tabla11312[[#This Row],[CANTIDAD]] -> 2901.12
A6: Lacoste | B6: Blanco Nuevo | C6: Varias | D6: =35+25+20+20+45+8+10+51 -> 214 | E6: Pares | F6: 15.11 | G6: =+Tabla11312[[#This Row],[PRECIO]]*Tabla11312[[#This Row],[CANTIDAD]] -> 3233.54
A7: Nautica | B7: Marino / Marinero | C7: Varias | D7: =13+12+5+14 -> 44 | E7: Pares | F7: 15.11 | G7: =+Tabla11312[[#This Row],[PRECIO]]*Tabla11312[[#This Row],[CANTIDAD]] -> 664.84
A8: Cons | B8: Café | C8: Varias | D8: =10+13+10+2+3+10+10+14+15+10+10+10+10+10+10+10+10+10+10+10+25+5+12 -> 239 | E8: Pares | F8: 15.11 | G8: =+Tabla11312[[#This Row],[PRECIO]]*Tabla11312[[#This Row],[CANTIDAD]] -> 3611.29
D9: =SUBTOTAL(109,Tabla11312[CANTIDAD]) -> 1253 | G9: =SUBTOTAL(109,Tabla11312[TOTAL]) -> 18620.65

Sheet suela sin  mov
B1: INVENTARIO DE SUELA
B2: ESTILO | C2: COLOR | D2: TALLA | E2: CANTIDAD | F2: PARES/NONES | G2: STATUS | H2: PRECIO | I2: TOTAL | J2: OBS
B3: AMERICAN | C3: BLANCA | D3: DAMA | E3: 1775 | F3: PARES | G3: SIN MOVIMIENTO | H3: 9.68 | I3: =+Tabla113[[#This Row],[CANTIDAD]]*Tabla113[[#This Row],[PRECIO]] -> 17182
B4: ASIA | C4: AMBAR | D4: VARIAS | E4: =895-895 -> 0 | F4: PARES | G4: SIN MOVIMIENTO | H4: 9.68 | I4: =+Tabla113[[#This Row],[CANTIDAD]]*Tabla113[[#This Row],[PRECIO]] -> 0 | J4: Eliminacion de material // 895
B5: CITY | C5: AMBAR | D5: DAMA | E5: =2900-2900 -> 0 | F5: PARES | G5: SIN MOVIMIENTO | H5: 9.68 | I5: =+Tabla113[[#This Row],[CANTIDAD]]*Tabla113[[#This Row],[PRECIO]] -> 0 | J5: Eliminacion de material // 2900
B6: CONS | C6: AMBAR | D6: VARIAS | E6: 1600 | F6: PARES | G6: SIN MOVIMIENTO | H6: 15.11 | I6: =+Tabla113[[#This Row],[CANTIDAD]]*Tabla113[[#This Row],[PRECIO]] -> 24176
B7: DANY | C7: AMBAR | D7: VARIAS | E7: 3155 | F7: PARES | G7: SIN MOVIMIENTO | H7: 12.69 | I7: =+Tabla113[[#This Row],[CANTIDAD]]*Tabla113[[#This Row],[PRECIO]] -> 40036.95
B8: DANY | C8: BLANCA | D8: VARIAS | E8: 1205 | F8: PARES | G8: SIN MOVIMIENTO | H8: 12.69 | I8: =+Tabla113[[#This Row],[CANTIDAD]]*Tabla113[[#This Row],[PRECIO]] -> 15291.45 | J8: Tono anterior
B9: DANY | C9: NEGRA | D9: VARIAS | E9: 3090 | F9: PARES | G9: SIN MOVIMIENTO | H9: 12.69 | I9: =+Tabla113[[#This Row],[CANTIDAD]]*Tabla113[[#This Row],[PRECIO]] -> 39212.1
B10: DC | C10: DC,AZUL MARINO-TRASSE | D10: VARIAS | E10: 296 | F10: PARES | G10: SIN MOVIMIENTO | H10: 14.31 | I10: =+Tabla113[[#This Row],[CANTIDAD]]*Tabla113[[#This Row],[PRECIO]] -> 4235.76
B11: DC | C11: DC,NEGRO-TRASSE | D11: VARIAS | E11: 793 | F11: PARES | G11: SIN MOVIMIENTO | H11: 14.31 | I11: =+Tabla113[[#This Row],[CANTIDAD]]*Tabla113[[#This Row],[PRECIO]] -> 11347.83
B12: DC | C12: DC,BLANCO-TRASSE | D12: VARIAS | E12: 881 | F12: PARES | G12: SIN MOVIMIENTO | H12: 14.31 | I12: =+Tabla113[[#This Row],[CANTIDAD]]*Tabla113[[#This Row],[PRECIO]] -> 12607.11
B13: DC | C13: DC,AMBAR-TRASSE | D13: VARIAS | E13: 459 | F13: PARES | G13: SIN MOVIMIENTO | H13: 14.31 | I13: =+Tabla113[[#This Row],[CANTIDAD]]*Tabla113[[#This Row],[PRECIO]] -> 6568.29
B14: DC | C14: DC,AZUL MARINO-TRASSE | D14: NONES | E14: 20 | F14: PARES | G14: SIN MOVIMIENTO | H14: 14.31 | I14: =+Tabla113[[#This Row],[CANTIDAD]]*Tabla113[[#This Row],[PRECIO]] -> 286.2
B15: DC | C15: DC,NEGRO-TRASSE | D15: NONES | E15: 5 | F15: PARES | G15: SIN MOVIMIENTO | H15: 14.31 | I15: =+Tabla113[[#This Row],[CANTIDAD]]*Tabla113[[#This Row],[PRECIO]] -> 71.55
B16: DC | C16: DC,BLANCO-TRASSE | D16: NONES | E16: 56 | F16: PARES | G16: SIN MOVIMIENTO | H16: 14.31 | I16: =+Tabla113[[#This Row],[CANTIDAD]]*Tabla113[[#This Row],[PRECIO]] -> 801.36
B17: DC | C17: DC,AMBAR-TRASSE | D17: NONES | E17: 10 | F17: PARES | G17: SIN MOVIMIENTO | H17: 14.31 | I17: =+Tabla113[[#This Row],[CANTIDAD]]*Tabla113[[#This Row],[PRECIO]] -> 143.1
B18: HARLEY | C18: AMBAR/INGERTO NEGRO | D18: RETRO | E18: 675 | F18: PARES | G18: SIN MOVIMIENTO | H18: 14.31 | I18: =+Tabla113[[#This Row],[CANTIDAD]]*Tabla113[[#This Row],[PRECIO]] -> 9659.25
B19: HARLEY | C19: AMBAR/INGERTO NEGRO | D19: MINIMAL | E19: 152 | F19: PARES | G19: SIN MOVIMIENTO | H19: 14.31 | I19: =+Tabla113[[#This Row],[CANTIDAD]]*Tabla113[[#This Row],[PRECIO]] -> 2175.12
B20: KAROSSO | C20: AMBAR | D20: VARIAS | E20: 464 | F20: PARES | G20: SIN MOVIMIENTO | H20: 14.31 | I20: =+Tabla113[[#This Row],[CANTIDAD]]*Tabla113[[#This Row],[PRECIO]] -> 6639.84
... B24: PAYLESS | C24: AMBAR | D24: CABALLERO | E24: 3754 | F24: PARES | G24: SIN MOVIMIENTO | H24: 9.68 | I24: =+Tabla113[[#This Row],[CANTIDAD]]*Tabla113[[#This Row],[PRECIO]] -> 36338.72
B25: PAYLESS | C25: AMBAR | D25: NIÑO | E25: =4980-4980 -> 0 | F25: PARES | G25: SIN MOVIMIENTO | H25: 9.68 | I25: =+Tabla113[[#This Row],[CANTIDAD]]*Tabla113[[#This Row],[PRECIO]] -> 0 | J25: Eliminacion de material // 4980
B26: PANAL | C26: MARINO | D26: VARIAS | E26: 1120 | F26: PARES | G26: SIN MOVIMIENTO | H26: 15.11 | I26: =+Tabla113[[#This Row],[CANTIDAD]]*Tabla113[[#This Row],[PRECIO]] -> 16923.2
B27: SKADI | C27: AMBAR | D27: VARIAS | E27: 1422 | F27: PARES | G27: SIN MOVIMIENTO | H27: 15.11 | I27: =+Tabla113[[#This Row],[CANTIDAD]]*Tabla113[[#This Row],[PRECIO]] -> 21486.42
B28: SKECHERS | C28: CAFÉ | D28: NIÑO | E28: 1130 | F28: PARES | G28: SIN MOVIMIENTO | H28: 9.68 | I28: =+Tabla113[[#This Row],[CANTIDAD]]*Tabla113[[#This Row],[PRECIO]] -> 10938.4
B29: SKECHERS | C29: CAFÉ | D29: NIÑA | E29: 1458 | F29: PARES | G29: SIN MOVIMIENTO | H29: 9.68 | I29: =+Tabla113[[#This Row],[CANTIDAD]]*Tabla113[[#This Row],[PRECIO]] -> 14113.44
B30: SKECHERS | C30: NEGRA | D30: H/M | E30: 823 | F30: PARES | G30: SIN MOVIMIENTO | H30: 9.68 | I30: =+Tabla113[[#This Row],[CANTIDAD]]*Tabla113[[#This Row],[PRECIO]] -> 7966.64
B31: SPERRY | C31: AMBAR | D31: VARIAS | E31: 1910 | F31: PARES | G31: SIN MOVIMIENTO | H31: 15.06 | I31: =+Tabla113[[#This Row],[CANTIDAD]]*Tabla113[[#This Row],[PRECIO]] -> 28764.6
B32: VANS | C32: GUM | D32: VARIAS | E32: 5069 | F32: PARES | G32: SIN MOVIMIENTO | H32: =0.98*20 -> 19.6 | I32: =+Tabla113[[#This Row],[CANTIDAD]]*Tabla113[[#This Row],[PRECIO]] -> 99352.4
B33: VANS | C33: BLACK | D33: VARIAS | E33: 4174 | F33: PARES | G33: SIN MOVIMIENTO | H33: =0.98*20 -> 19.6 | I33: =+Tabla113[[#This Row],[CANTIDAD]]*Tabla113[[#This Row],[PRECIO]] -> 81810.4
B34: VANS | C34: PEARL WHITE | D34: VARIAS | E34: 5039 | F34: PARES | G34: SIN MOVIMIENTO | H34: =0.98*20 -> 19.6 | I34: =+Tabla113[[#This Row],[CANTIDAD]]*Tabla113[[#This Row],[PRECIO]] -> 98764.4
E35: =SUBTOTAL(109,Tabla113[CANTIDAD]) -> 46449 | I35: =SUBTOTAL(109,Tabla113[TOTAL]) -> 664417.85

Sheet Almacén_MateriaPrima
B1: Tipo de cambio | C1: 18.02 | D1: 46010 | E1: Banco de Mx | F1: PRECIO NO INCLUYE IVA
A2: INVENTARIO | B2: CANTIDAD | C2: PRECIO | D2: UNIDAD | E2: Importe | F2: OBSERVACIONES
A3: CANDADO 28 mm | B3: =3*2.5 -> 7.5 | C3: 76 | D3: x MILLAR | E3: =Tabla8[[#This Row],[CANTIDAD]]*Tabla8[[#This Row],[PRECIO]] -> 570
A4: CANDADO 31 mm | B4: =5*2.5 -> 12.5 | C4: 76 | D4: x MILLAR | E4: =Tabla8[[#This Row],[CANTIDAD]]*Tabla8[[#This Row],[PRECIO]] -> 950
A5: CANDADO 37 mm | B5: =11*2.5 -> 27.5 | C5: 85 | D5: x MILLAR | E5: =Tabla8[[#This Row],[CANTIDAD]]*Tabla8[[#This Row],[PRECIO]] -> 2337.5
A6: CANDADO 40 mm | B6: =4*2.5 -> 10 | C6: 106.8965 | D6: x MILLAR | E6: =Tabla8[[#This Row],[CANTIDAD]]*Tabla8[[#This Row],[PRECIO]] -> 1068.965
A7: CANDADO 43 mm | B7: =3*2.5 -> 7.5 | C7: 63.44 | D7: x MILLAR | E7: =Tabla8[[#This Row],[CANTIDAD]]*Tabla8[[#This Row],[PRECIO]] -> 475.8
A8: CANDADO 46 mm | B8: =3*2.5 -> 7.5 | C8: 63.44 | D8: x MILLAR | E8: =Tabla8[[#This Row],[CANTIDAD]]*Tabla8[[#This Row],[PRECIO]] -> 475.8
A9: CANDADO 49 mm | B9: =6*2.5 -> 15 | C9: 63.44 | D9: x MILLAR | E9: =Tabla8[[#This Row],[CANTIDAD]]*Tabla8[[#This Row],[PRECIO]] -> 951.6
A10: CANDADO 52 mm | B10: 0 | C10: 199 | D10: x MILLAR | E10: =Tabla8[[#This Row],[CANTIDAD]]*Tabla8[[#This Row],[PRECIO]] -> 0
A11: CANDADO 55 mm | B11: =5*2.5 -> 12.5 | C11: 63.444 | D11: x MILLAR | E11: =Tabla8[[#This Row],[CANTIDAD]]*Tabla8[[#This Row],[PRECIO]] -> 793.05
A12: CANDADO 61 mm | B12: 0 | C12: 63.444 | D12: x MILLAR | E12: =Tabla8[[#This Row],[CANTIDAD]]*Tabla8[[#This Row],[PRECIO]] -> 0
A13: CANDADO 64 mm | B13: =3*2.5 -> 7.5 | C13: 76 | D13: x MILLAR | E13: =Tabla8[[#This Row],[CANTIDAD]]*Tabla8[[#This Row],[PRECIO]] -> 570
A14: CANDADO 67 mm | B14: =2*2.5 -> 5 | C14: 76 | D14: x MILLAR | E14: =Tabla8[[#This Row],[CANTIDAD]]*Tabla8[[#This Row],[PRECIO]] -> 380
A15: CANDADO 70 mm | B15: 0 | C15: 76 | D15: x MILLAR | E15: =Tabla8[[#This Row],[CANTIDAD]]*Tabla8[[#This Row],[PRECIO]] -> 0
A16: PLASTI FLECHA ITEM NR 20PP | B16: 1 | C16: 54.37 | D16: X CAJA (5'000 piezas) | E16: =Tabla8[[#This Row],[CANTIDAD]]*Tabla8[[#This Row],[PRECIO]] -> 54.37
A17: CANDADO LISO 3" | D17: X CAJA (5'000 piezas) | E17: =Tabla8[[#This Row],[CANTIDAD]]*Tabla8[[#This Row],[PRECIO]] -> 0 | F17: Importado
A18: CANDADO LISO 5" | B18: 1 | C18: 189.24 | D18: X CAJA (5'000 piezas) | E18: =Tabla8[[#This Row],[CANTIDAD]]*Tabla8[[#This Row],[PRECIO]] -> 189.24
A19: SILICÓN GRUESO | B19: =2+2 -> 4 | C19: 106.27 | D19: KG | E19: =Tabla8[[#This Row],[CANTIDAD]]*Tabla8[[#This Row],[PRECIO]] -> 425.08
A20: PAPEL COLLEC 30 X 65 | B20: 3 | C20: 505.82 | D20: x MILLAR | E20: =Tabla8[[#This Row],[CANTIDAD]]*Tabla8[[#This Row],[PRECIO]] -> 1517.46 | F20: El precio por millar de este material, con base a una medida 70*90 cm, de la cual se saca cada corte que utilizamos, por ejemplo: En la medida 30*65, son tres cortes del millar de papel de 70*90.
A21: PAPEL COLLEC 36 X 70 | B21: 0 | C21: 505.82 | D21: x MILLAR | E21: =Tabla8[[#This Row],[CANTIDAD]]*Tabla8[[#This Row],[PRECIO]] -> 0
A22: PAPEL COLLEC 40 X 70 | B22: 4 | C22: 505.82 | D22: x MILLAR | E22: =Tabla8[[#This Row],[CANTIDAD]]*Tabla8[[#This Row],[PRECIO]] -> 2023.28 | F22: El precio por millar de este material, con base a una medida 70*90 cm, de la cual se saca cada corte que utilizamos, por ejemplo: En la medida 30*65, son tres cortes del millar de papel de 70*90.
A23: PAPEL DE CHINA BLANCO 15 X 60 | B23: 0 | C23: 0 | D23: x MILLAR | E23: =Tabla8[[#This Row],[CANTIDAD]]*Tabla8[[#This Row],[PRECIO]] -> 0
A24: PAPEL DE CHINA BLANCO 21 X 60 | B24: 0 | C24: 0 | D24: x MILLAR | E24: =Tabla8[[#This Row],[CANTIDAD]]*Tabla8[[#This Row],[PRECIO]] -> 0
A25: PAPEL DE CHINA BLANCO 15 X 70 | B25: 0 | C25: 0 | D25: x MILLAR | E25: =Tabla8[[#This Row],[CANTIDAD]]*Tabla8[[#This Row],[PRECIO]] -> 0
A26: PAPEL DE CHINA BLANCO 25 X 70 | B26: 0 | C26: 0 | D26: x MILLAR | E26: =Tabla8[[#This Row],[CANTIDAD]]*Tabla8[[#This Row],[PRECIO]] -> 0
A27: PAPEL DE CHINA BLANCO 18 X 70 | B27: 0 | C27: 0 | D27: x MILLAR | E27: =Tabla8[[#This Row],[CANTIDAD]]*Tabla8[[#This Row],[PRECIO]] -> 0
A28: PAPEL DE CHINA BLANCO 27 X 70 | B28: 0 | C28: 0 | D28: x MILLAR | E28: =Tabla8[[#This Row],[CANTIDAD]]*Tabla8[[#This Row],[PRECIO]] -> 0
A29: ESTOPA | B29: 0 | C29: 1219 | D29: PACA (50 kg) | E29: =Tabla8[[#This Row],[CANTIDAD]]*Tabla8[[#This Row],[PRECIO]] -> 0
A30: ESCOBAS | B30: 3 | C30: 35 | D30: PZA | E30: =Tabla8[[#This Row],[CANTIDAD]]*Tabla8[[#This Row],[PRECIO]] -> 105
A31: TACHUELAS | B31: 19 | C31: 216.2 | D31: CAJA/1000 | E31: =Tabla8[[#This Row],[CANTIDAD]]*Tabla8[[#This Row],[PRECIO]] -> 4107.8
A32: HOTMELT | B32: 0 | C32: 149 | D32: KG | E32: =Tabla8[[#This Row],[CANTIDAD]]*Tabla8[[#This Row],[PRECIO]] -> 0
A33: PAPEL HIGIENICO(12) | B33: 0 | C33: 0 | D33: CAJA /12 | E33: =Tabla8[[#This Row],[CANTIDAD]]*Tabla8[[#This Row],[PRECIO]] -> 0
A34: GUANTES BLANCO (12) | B34: =4*12 -> 48 | C34: =13.38*0.9 -> 12.042 | D34: PZA | E34: =Tabla8[[#This Row],[CANTIDAD]]*Tabla8[[#This Row],[PRECIO]] -> 578.016
A35: GUANTES GRIS JAPONES(12) | B35: =1*12 -> 12 | C35: =8.28*0.9 -> 7.452 | D35: PZA | E35: =Tabla8[[#This Row],[CANTIDAD]]*Tabla8[[#This Row],[PRECIO]] -> 89.424
A36: FUNDA MOP 60 CM (CHICA) | B36: 2 | C36: 69 | D36: PZA | E36: =Tabla8[[#This Row],[CANTIDAD]]*Tabla8[[#This Row],[PRECIO]] -> 138
A37: FUNDA MOP 90 CM (MEDIANA) | B37: 4 | C37: 92 | D37: PZA | E37: =Tabla8[[#This Row],[CANTIDAD]]*Tabla8[[#This Row],[PRECIO]] -> 368
A38: FUNDA MOP 125 CM (GRANDE) | B38: 2 | C38: 99 | D38: PZA | E38: =Tabla8[[#This Row],[CANTIDAD]]*Tabla8[[#This Row],[PRECIO]] -> 198
A39: RODILLO QUITA PELUSA (80 HOJAS) | B39: 11 | C39: 86.63 | D39: PZA | E39: =Tabla8[[#This Row],[CANTIDAD]]*Tabla8[[#This Row],[PRECIO]] -> 952.93
A40: PEGAMENTO GREEN | B40: 51 | C40: 34.05 | D40: PZA | E40: =Tabla8[[#This Row],[CANTIDAD]]*Tabla8[[#This Row],[PRECIO]] -> 1736.55
A41: MASCARILLA N95 8511MX | B41: 10 | C41: 46.75 | D41: PZA | E41: =Tabla8[[#This Row],[CANTIDAD]]*Tabla8[[#This Row],[PRECIO]] -> 467.5
A42: TAPONES PARA OÍDO | B42: 15 | C42: 4.75 | D42: PZA | E42: =Tabla8[[#This Row],[CANTIDAD]]*Tabla8[[#This Row],[PRECIO]] -> 71.25
A43: GUANTE DE NITRILO (TALLA M) | B43: 1.5 | C43: 275.83 | D43: CAJA / 100 PZS | E43: =Tabla8[[#This Row],[CANTIDAD]]*Tabla8[[#This Row],[PRECIO]] -> 413.745
A44: LENTE ANTIPAÑO TRANSPARENTE | B44: 8 | C44: 19.24 | D44: PZA | E44: =Tabla8[[#This Row],[CANTIDAD]]*Tabla8[[#This Row],[PRECIO]] -> 153.92
A45: FLEJE BLANCO / TRANSPARENTE | B45: 2 | C45: 1093.68 | D45: PZA/3000 MTS | E45: =Tabla8[[#This Row],[CANTIDAD]]*Tabla8[[#This Row],[PRECIO]] -> 2187.36
A46: FLEJE AMARILLO 15mm | B46: 15 | C46: 301.73 | D46: PZA/1500 MTS aprox | E46: =Tabla8[[#This Row],[CANTIDAD]]*Tabla8[[#This Row],[PRECIO]] -> 4525.95
A47: ARF-1000 | B47: 0 | C47: 524.5 | D47: PZA | E47: =Tabla8[[#This Row],[CANTIDAD]]*Tabla8[[#This Row],[PRECIO]] -> 0
... A53: CINTA VERDE | B53: 0 | C53: 50 | D53: PZA | E53: =Tabla8[[#This Row],[CANTIDAD]]*Tabla8[[#This Row],[PRECIO]] -> 0
A54: CINTA ROJA | B54: 24 | C54: =53.18*0.9 -> 47.862 | D54: PZA | E54: =Tabla8[[#This Row],[CANTIDAD]]*Tabla8[[#This Row],[PRECIO]] -> 1148.688
A55: CINTA AZUL (KEDS) | B55: 18 | C55: 34.5 | D55: PZA | E55: =Tabla8[[#This Row],[CANTIDAD]]*Tabla8[[#This Row],[PRECIO]] -> 621
A56: CINTA IMPRESA SKECHERS | B56: 48 | C56: 73 | D56: PZA | E56: =Tabla8[[#This Row],[CANTIDAD]]*Tabla8[[#This Row],[PRECIO]] -> 3504
A57: CINTA IMPRESA SUPERGA | B57: 167 | C57: 125.9 | D57: PZA | E57: =Tabla8[[#This Row],[CANTIDAD]]*Tabla8[[#This Row],[PRECIO]] -> 21025.3
A58: CINTA IMPRESA KEEN | B58: 120 | C58: 82 | D58: PZA | E58: =Tabla8[[#This Row],[CANTIDAD]]*Tabla8[[#This Row],[PRECIO]] -> 9840 | F58: *REVISAR / No se encuentran
A59: CINTA IMPRESA CHARLY | B59: 0 | C59: 60 | D59: PZA | E59: =Tabla8[[#This Row],[CANTIDAD]]*Tabla8[[#This Row],[PRECIO]] -> 0
A60: CINTA IMPRESA COLLEC | B60: 120 | C60: 60 | D60: PZA | E60: =Tabla8[[#This Row],[CANTIDAD]]*Tabla8[[#This Row],[PRECIO]] -> 7200
A61: CINTA IMPRESA LACOSTE | B61: 0 | C61: 84 | D61: PZA | E61: =Tabla8[[#This Row],[CANTIDAD]]*Tabla8[[#This Row],[PRECIO]] -> 0
A62: ETIQ. COLGANTE COLLEC | B62: =19366/1000 -> 19.366 | C62: 236.4 | D62: MILLAR | E62: =Tabla8[[#This Row],[CANTIDAD]]*Tabla8[[#This Row],[PRECIO]] -> 4578.1224
A63: ETIQ. LAVADO | B63: 0 | C63: 168.66 | D63: MILLAR | E63: =Tabla8[[#This Row],[CANTIDAD]]*Tabla8[[#This Row],[PRECIO]] -> 0
A64: ETIQ. ANTIDERRAPANTE URBAN | B64: 2 | C64: 3 | D64: MILLAR | E64: =Tabla8[[#This Row],[CANTIDAD]]*Tabla8[[#This Row],[PRECIO]] -> 6
A65: Ojillo Plata/ Collec | B65: =3*10 -> 30 | C65: 40.3 | D65: Millar | E65: =Tabla8[[#This Row],[CANTIDAD]]*Tabla8[[#This Row],[PRECIO]] -> 1209
A66: OJILLO PLATA 877 8MM | B66: 10.7 | C66: 67.82 | D66: Millar | E66: =Tabla8[[#This Row],[CANTIDAD]]*Tabla8[[#This Row],[PRECIO]] -> 725.674
A67: OJILLO MARINO 540 8MM | B67: 7 | C67: 67.82 | D67: Millar | E67: =Tabla8[[#This Row],[CANTIDAD]]*Tabla8[[#This Row],[PRECIO]] -> 474.74
A68: OJILLO MARINO 739 8MM | B68: 4.5 | C68: 67.82 | D68: Millar | E68: =Tabla8[[#This Row],[CANTIDAD]]*Tabla8[[#This Row],[PRECIO]] -> 305.19
A69: OJILLO ROJO E20 8MM | B69: 47.8 | C69: 67.82 | D69: Millar | E69: =Tabla8[[#This Row],[CANTIDAD]]*Tabla8[[#This Row],[PRECIO]] -> 3241.796
A70: OJILLO LATÓN VIEJO 8MM | B70: 4.5 | C70: 74.02 | D70: Millar | E70: =Tabla8[[#This Row],[CANTIDAD]]*Tabla8[[#This Row],[PRECIO]] -> 333.09
A71: OJILLO ESMALTADO NEGRO E50 8MM | B71: =3*4 -> 12 | C71: 87.64 | D71: Millar | E71: =Tabla8[[#This Row],[CANTIDAD]]*Tabla8[[#This Row],[PRECIO]] -> 1051.68
A72: OJILLO VINO 8MM | B72: 1.35 | C72: 67.82 | D72: MILLAR | E72: =Tabla8[[#This Row],[CANTIDAD]]*Tabla8[[#This Row],[PRECIO]] -> 91.557
A73: OJILLO DORADO | B73: 2.9 | C73: 40.3 | D73: Millar | E73: =Tabla8[[#This Row],[CANTIDAD]]*Tabla8[[#This Row],[PRECIO]] -> 116.87 | F73: Importado
A74: OJILLO AZUL CIELO 8MM | B74: 5.1 | C74: 67.82 | D74: Millar | E74: =Tabla8[[#This Row],[CANTIDAD]]*Tabla8[[#This Row],[PRECIO]] -> 345.882
A75: OJILLO GRIS 027 8MM | B75: 5.3 | C75: 88.99 | D75: Millar | E75: =Tabla8[[#This Row],[CANTIDAD]]*Tabla8[[#This Row],[PRECIO]] -> 471.647
A76: OJILLO HD 8mm aprox | B76: 104.432 | C76: 40.3 | D76: MILLAR | E76: =Tabla8[[#This Row],[CANTIDAD]]*Tabla8[[#This Row],[PRECIO]] -> 4208.6096 | F76: Importado
A77: OJILLO CAFÉ CHINA 8mm aprox | B77: 9.5 | C77: 40.3 | D77: Millar | E77: =Tabla8[[#This Row],[CANTIDAD]]*Tabla8[[#This Row],[PRECIO]] -> 382.85 | F77: Importado
A78: OJILLO GRIS CHINA 8mm aprox | B78: 16.725 | C78: 40.3 | D78: Millar | E78: =Tabla8[[#This Row],[CANTIDAD]]*Tabla8[[#This Row],[PRECIO]] -> 674.0175 | F78: Importado
A79: TRAPEADORES | B79: 2 | C79: 39.22 | D79: PZA | E79: =Tabla8[[#This Row],[CANTIDAD]]*Tabla8[[#This Row],[PRECIO]] -> 78.44
A80: PAPEL IMP-URBAN | B80: 3 | C80: 200 | D80: MILLAR | E80: =Tabla8[[#This Row],[CANTIDAD]]*Tabla8[[#This Row],[PRECIO]] -> 600
A81: PAPEL CORE 40X70 | B81: 0 | C81: 379.53 | D81: MILLAR | E81: =Tabla8[[#This Row],[CANTIDAD]]*Tabla8[[#This Row],[PRECIO]] -> 0
A82: PAPEL IMPRESO BLANX | B82: 0.5 | C82: 1100 | D82: MILLAR | E82: =Tabla8[[#This Row],[CANTIDAD]]*Tabla8[[#This Row],[PRECIO]] -> 550
A83: PAPEL IMPRESO POLO | B83: 2.25 | C83: 262 | D83: MILLAR | E83: =Tabla8[[#This Row],[CANTIDAD]]*Tabla8[[#This Row],[PRECIO]] -> 589.5
A84: PAPEL IMPRESO GOODYEAR | B84: 1 | C84: 296 | D84: MILLAR | E84: =Tabla8[[#This Row],[CANTIDAD]]*Tabla8[[#This Row],[PRECIO]] -> 296
A85: PAPEL IMPRESO NEXT & CO | B85: 0.25 | C85: 296 | D85: MILLAR | E85: =Tabla8[[#This Row],[CANTIDAD]]*Tabla8[[#This Row],[PRECIO]] -> 74
A86: PAPEL IMPRESO BELINDA | B86: =374/1000 -> 0.374 | C86: 340 | D86: MILLAR | E86: =Tabla8[[#This Row],[CANTIDAD]]*Tabla8[[#This Row],[PRECIO]] -> 127.16
A87: PAPEL IMPRESO SKECHERS 21.5 X 90 CM | B87: 0.25 | C87: 300 | D87: MILLAR | E87: =Tabla8[[#This Row],[CANTIDAD]]*Tabla8[[#This Row],[PRECIO]] -> 75
A88: PAPEL IMPRESO SKECHERS 18 X 90 CM | B88: 1 | C88: 200 | D88: MILLAR | E88: =Tabla8[[#This Row],[CANTIDAD]]*Tabla8[[#This Row],[PRECIO]] -> 200
A89: PAPEL IMPRESO SUPERGA | B89: 2.25 | C89: 400 | D89: MILLAR | E89: =Tabla8[[#This Row],[CANTIDAD]]*Tabla8[[#This Row],[PRECIO]] -> 900
A90: PAPEL HARLEY DAVISON GRANDE | B90: 1 | C90: 610 | D90: MILLAR | E90: =Tabla8[[#This Row],[CANTIDAD]]*Tabla8[[#This Row],[PRECIO]] -> 610
A91: PAPEL HARLEY DAVISON CHICO | B91: 0 | C91: 340 | D91: MILLAR | E91: =Tabla8[[#This Row],[CANTIDAD]]*Tabla8[[#This Row],[PRECIO]] -> 0
A92: PAPEL IMPRESO LACOSTE 16 X 76 CM | B92: 1.581 | C92: 160 | D92: MILLAR | E92: =Tabla8[[#This Row],[CANTIDAD]]*Tabla8[[#This Row],[PRECIO]] -> 252.96
A93: PAPEL IMPRESO LACOSTE 19 X 86 CM | B93: 0.5 | C93: 220 | D93: MILLAR | E93: =Tabla8[[#This Row],[CANTIDAD]]*Tabla8[[#This Row],[PRECIO]] -> 110
A94: PAPEL IMPRESO LACOSTE 27 X 68 CM | B94: 1.836 | C94: 260 | D94: MILLAR | E94: =Tabla8[[#This Row],[CANTIDAD]]*Tabla8[[#This Row],[PRECIO]] -> 477.36
A95: PAPEL IMPRESO LACOSTE 31 X 74 CM | B95: 0.05 | C95: 280 | D95: MILLAR | E95: =Tabla8[[#This Row],[CANTIDAD]]*Tabla8[[#This Row],[PRECIO]] -> 14
A96: Papel Celofán | B96: 75 | C96: 68.97 | D96: KG | E96: =Tabla8[[#This Row],[CANTIDAD]]*Tabla8[[#This Row],[PRECIO]] -> 5172.75
A97: HILO DEL 30 BLANCO P/JARETA LEON CONO AZUL | B97: 0 | C97: 25.3 | D97: PZA | E97: =Tabla8[[#This Row],[CANTIDAD]]*Tabla8[[#This Row],[PRECIO]] -> 0
A98: HILO DEL 30 BLANCO P/JARETA LEON CONO BLANCO | B98: 18 | C98: 15.52 | D98: PZA | E98: =Tabla8[[#This Row],[CANTIDAD]]*Tabla8[[#This Row],[PRECIO]] -> 279.36
... A100: PELÍCULA PLÁSTICA | B100: 1 | C100: 117.68 | D100: ROLLO | E100: =Tabla8[[#This Row],[CANTIDAD]]*Tabla8[[#This Row],[PRECIO]] -> 117.68
A101: BOLSA 25 X 35 | B101: =1*25 -> 25 | C101: 37.28 | D101: KG | E101: =Tabla8[[#This Row],[CANTIDAD]]*Tabla8[[#This Row],[PRECIO]] -> 932
A102: BOLSA 30 X 40 URBAN | B102: =2*25 -> 50 | C102: 37.28 | D102: KG | E102: =Tabla8[[#This Row],[CANTIDAD]]*Tabla8[[#This Row],[PRECIO]] -> 1864
A103: BOLSA 40 X 60 | B103: =2*25 -> 50 | C103: 37.38 | D103: KG | E103: =Tabla8[[#This Row],[CANTIDAD]]*Tabla8[[#This Row],[PRECIO]] -> 1869
A104: BOLSA NEGRA JUMBO | B104: 0 | C104: 47.59 | D104: KG | E104: =Tabla8[[#This Row],[CANTIDAD]]*Tabla8[[#This Row],[PRECIO]] -> 0
A105: BOLSA 70 X 90 | B105: =5*25 -> 125 | C105: 36.5 | D105: KG | E105: =Tabla8[[#This Row],[CANTIDAD]]*Tabla8[[#This Row],[PRECIO]] -> 4562.5
A106: GEL ANTIBACTERIAL | B106: 5 | C106: 41.74 | D106: LTO | E106: =Tabla8[[#This Row],[CANTIDAD]]*Tabla8[[#This Row],[PRECIO]] -> 208.7
...

Sheet Caja Individual
A1: CODIGO | B1: MARCA | C1: MEDIDA | D1: CANTIDAD | E1: Costo Unitario | F1: Importe | G1: OBS
A2: 7047 | B2: AIRWALK | C2: 1 | D2: 255 | E2: 8.66 | F2: =Tabla4[[#This Row],[CANTIDAD]]*Tabla4[[#This Row],[Costo Unitario]] -> 2208.3
A3: 7096 | B3: BLANX | C3: 1 | D3: 450 | E3: 8.7 | F3: =Tabla4[[#This Row],[CANTIDAD]]*Tabla4[[#This Row],[Costo Unitario]] -> 3915
A4: 7022 | B4: COLLEC | C4: 15 / 17½ | D4: 2250 | E4: 3.6 | F4: =Tabla4[[#This Row],[CANTIDAD]]*Tabla4[[#This Row],[Costo Unitario]] -> 8100
A5: 7017 | B5: COLLEC | C5: 18 / 21 | D5: 2750 | E5: 4.1 | F5: =Tabla4[[#This Row],[CANTIDAD]]*Tabla4[[#This Row],[Costo Unitario]] -> 11275
A6: 7036 | B6: COLLEC | C6: 22 / 25 | D6: 10000 | E6: 4.6 | F6: =Tabla4[[#This Row],[CANTIDAD]]*Tabla4[[#This Row],[Costo Unitario]] -> 46000
A7: 7000 | B7: COLLEC | C7: 25 / 28 | D7: 6250 | E7: 4.85 | F7: =Tabla4[[#This Row],[CANTIDAD]]*Tabla4[[#This Row],[Costo Unitario]] -> 30312.5
A8: 7055 | B8: CORE | C8: CHICA | D8: 0 | E8: 9.07 | F8: =Tabla4[[#This Row],[CANTIDAD]]*Tabla4[[#This Row],[Costo Unitario]] -> 0
A9: 7028 | B9: CORE | C9: GRANDE | D9: 400 | E9: 8.65 | F9: =Tabla4[[#This Row],[CANTIDAD]]*Tabla4[[#This Row],[Costo Unitario]] -> 3460
A10: * | B10: CORE | C10: EDICION ESPE. | D10: 361 | E10: 0 | F10: =Tabla4[[#This Row],[CANTIDAD]]*Tabla4[[#This Row],[Costo Unitario]] -> 0 | G10: Sin costo
A11: 16765 | B11: DC | C11: CHICA Diseño 2024 | D11: 350 | E11: 6.35 | F11: =Tabla4[[#This Row],[CANTIDAD]]*Tabla4[[#This Row],[Costo Unitario]] -> 2222.5
A12: 16766 | B12: DC | C12: GRANDE Diseño 2024 | D12: 200 | E12: 7.86 | F12: =Tabla4[[#This Row],[CANTIDAD]]*Tabla4[[#This Row],[Costo Unitario]] -> 1572
A13: 7118 | B13: GOODYEAR | C13: 33X14X12cm | D13: 891 | E13: 10.29 | F13: =Tabla4[[#This Row],[CANTIDAD]]*Tabla4[[#This Row],[Costo Unitario]] -> 9168.39
A14: 7044 | B14: HARLEY DAVIDSON | C14: CHICA | D14: 0 | E14: 4.82 | F14: =Tabla4[[#This Row],[CANTIDAD]]*Tabla4[[#This Row],[Costo Unitario]] -> 0 | G14: Caja desde 2018
A15: 7027 | B15: HARLEY DAVIDSON | C15: MEDIANA | D15: 278 | E15: 8.57 | F15: =Tabla4[[#This Row],[CANTIDAD]]*Tabla4[[#This Row],[Costo Unitario]] -> 2382.46
A16: 7048 | B16: HARLEY DAVIDSON | C16: GRANDE | D16: 809 | E16: 8.86 | F16: =Tabla4[[#This Row],[CANTIDAD]]*Tabla4[[#This Row],[Costo Unitario]] -> 7167.74
A17: 7110 | B17: HARLEY DAVIDSON | C17: XG | D17: 100 | E17: 9.31 | F17: =Tabla4[[#This Row],[CANTIDAD]]*Tabla4[[#This Row],[Costo Unitario]] -> 931
A18: * | B18: HARLEY SIN IMPRESIÓN | C18: GRANDE | D18: 271 | E18: 8.86 | F18: =Tabla4[[#This Row],[CANTIDAD]]*Tabla4[[#This Row],[Costo Unitario]] -> 2401.06 | G18: Blanx - abril 2022
A19: 16787 | B19: KITS | C19: CH 20.3*15*8.5 CM | D19: 533 | E19: 18 | F19: =Tabla4[[#This Row],[CANTIDAD]]*Tabla4[[#This Row],[Costo Unitario]] -> 9594
A20: 16788 | B20: KITS | C20: GDE 26*16*10 CM | D20: 260 | E20: 19.9 | F20: =Tabla4[[#This Row],[CANTIDAD]]*Tabla4[[#This Row],[Costo Unitario]] -> 5174
A21: 7120 | B21: LACOSTE | C21: 280 | D21: 0 | E21: 10.81 | F21: =Tabla4[[#This Row],[CANTIDAD]]*Tabla4[[#This Row],[Costo Unitario]] -> 0
A22: 7121 | B22: LACOSTE | C22: 310 | D22: 266 | E22: 11.85 | F22: =Tabla4[[#This Row],[CANTIDAD]]*Tabla4[[#This Row],[Costo Unitario]] -> 3152.1
A23: 7122 | B23: LACOSTE | C23: 330 | D23: 66 | E23: 12.5 | F23: =Tabla4[[#This Row],[CANTIDAD]]*Tabla4[[#This Row],[Costo Unitario]] -> 825
A24: 7108 | B24: NAUTICA DAMA | C24: 30*18.5*12 | D24: 30 | E24: 11.65 | F24: =Tabla4[[#This Row],[CANTIDAD]]*Tabla4[[#This Row],[Costo Unitario]] -> 349.5
A25: 7109 | B25: NAUTICA CABALLERO | C25: 33*18.5*11 | D25: 320 | E25: 9.11 | F25: =Tabla4[[#This Row],[CANTIDAD]]*Tabla4[[#This Row],[Costo Unitario]] -> 2915.2
A26: 7128 | B26: NAUTICA CABALLERO | C26: 33*22*12 | D26: 10 | E26: 11.94 | F26: =Tabla4[[#This Row],[CANTIDAD]]*Tabla4[[#This Row],[Costo Unitario]] -> 119.4
A27: 7119 | B27: NEXT & CO RONY | C27: 31*21.5*11.5 | D27: 19 | E27: 9.22 | F27: =Tabla4[[#This Row],[CANTIDAD]]*Tabla4[[#This Row],[Costo Unitario]] -> 175.18
A28: 7080 | B28: POLO | C28: 29.5*163.5*10.5*4 | D28: 133 | E28: 7.31 | F28: =Tabla4[[#This Row],[CANTIDAD]]*Tabla4[[#This Row],[Costo Unitario]] -> 972.23
A29: 7082 | B29: SKECHERS | C29: CABALLERO GDE | D29: 116 | E29: 10.56 | F29: =Tabla4[[#This Row],[CANTIDAD]]*Tabla4[[#This Row],[Costo Unitario]] -> 1224.96
A30: 7083 | B30: SKECHERS | C30: CABALLERO CH | D30: 954 | E30: 7.48 | F30: =Tabla4[[#This Row],[CANTIDAD]]*Tabla4[[#This Row],[Costo Unitario]] -> 7135.92
A31: 7081 | B31: SKECHERS | C31: DAMA GDE | D31: 81 | E31: 8.27 | F31: =Tabla4[[#This Row],[CANTIDAD]]*Tabla4[[#This Row],[Costo Unitario]] -> 669.87
A32: 7079 | B32: SKECHERS | C32: DAMA CH | D32: 229 | E32: 7.48 | F32: =Tabla4[[#This Row],[CANTIDAD]]*Tabla4[[#This Row],[Costo Unitario]] -> 1712.92
A33: 7084 | B33: SKECHERS | C33: NIÑA CH | D33: 1100 | E33: 3.4 | F33: =Tabla4[[#This Row],[CANTIDAD]]*Tabla4[[#This Row],[Costo Unitario]] -> 3740 | G33: Caja desde 2021
A34: 7085 | B34: SKECHERS | C34: NIÑA MD | D34: 460 | E34: 4.2 | F34: =Tabla4[[#This Row],[CANTIDAD]]*Tabla4[[#This Row],[Costo Unitario]] -> 1932 | G34: Caja desde 2021
A35: 7074 | B35: SKECHERS | C35: #1 | D35: 1539 | E35: 4.99 | F35: =Tabla4[[#This Row],[CANTIDAD]]*Tabla4[[#This Row],[Costo Unitario]] -> 7679.61
A36: 7076 | B36: SKECHERS | C36: #3 | D36: 3471 | E36: 5.4 | F36: =Tabla4[[#This Row],[CANTIDAD]]*Tabla4[[#This Row],[Costo Unitario]] -> 18743.4
A37: 7078 | B37: SKECHERS | C37: #5 | D37: 4691 | E37: 7.33 | F37: =Tabla4[[#This Row],[CANTIDAD]]*Tabla4[[#This Row],[Costo Unitario]] -> 34385.03
A38: 7105 | B38: SKECHERS (KRAFT) | C38: 225 | D38: 1282 | E38: 4.59 | F38: =Tabla4[[#This Row],[CANTIDAD]]*Tabla4[[#This Row],[Costo Unitario]] -> 5884.38
A39: 7106 | B39: SKECHERS (KRAFT) | C39: 260 | D39: 780 | E39: 4.94 | F39: =Tabla4[[#This Row],[CANTIDAD]]*Tabla4[[#This Row],[Costo Unitario]] -> 3853.2
A40: 7107 | B40: SKECHERS (KRAFT) | C40: 305 | D40: 1050 | E40: 6.7 | F40: =Tabla4[[#This Row],[CANTIDAD]]*Tabla4[[#This Row],[Costo Unitario]] -> 7035
A41: 7058 | B41: SUPERGA | C41: 280 | D41: 361 | E41: 16.91 | F41: =Tabla4[[#This Row],[CANTIDAD]]*Tabla4[[#This Row],[Costo Unitario]] -> 6104.51
A42: 7057 | B42: SUPERGA | C42: 315 | D42: 392 | E42: 17.42 | F42: =Tabla4[[#This Row],[CANTIDAD]]*Tabla4[[#This Row],[Costo Unitario]] -> 6828.64
A43: 7056 | B43: SUPERGA | C43: 345 | D43: 523 | E43: 12.11 | F43: =Tabla4[[#This Row],[CANTIDAD]]*Tabla4[[#This Row],[Costo Unitario]] -> 6333.53 | G43: Importación
A44: * | B44: SUPERGA | C44: PLATAFORMA | D44: 716 | E44: 31.09 | F44: =Tabla4[[#This Row],[CANTIDAD]]*Tabla4[[#This Row],[Costo Unitario]] -> 22260.44 | G44: Importación
A45: 7008 | B45: URBAN | C45: CHANCLETA | D45: 0 | E45: 3.38 | F45: =Tabla4[[#This Row],[CANTIDAD]]*Tabla4[[#This Row],[Costo Unitario]] -> 0
A46: 7045 | B46: URBAN | C46: CABALLERO | D46: 2100 | E46: 6 | F46: =Tabla4[[#This Row],[CANTIDAD]]*Tabla4[[#This Row],[Costo Unitario]] -> 12600
A47: 10541 | B47: VANS | C47: A4 | D47: 0 | E47: 6.85 | F47: =Tabla4[[#This Row],[CANTIDAD]]*Tabla4[[#This Row],[Costo Unitario]] -> 0
A48: 10542 | B48: VANS | C48: A5 | D48: 11865 | E48: 6.85 | F48: =Tabla4[[#This Row],[CANTIDAD]]*Tabla4[[#This Row],[Costo Unitario]] -> 81275.25
A49: 10543 | B49: VANS | C49: AO | D49: 6313 | E49: 6.85 | F49: =Tabla4[[#This Row],[CANTIDAD]]*Tabla4[[#This Row],[Costo Unitario]] -> 43244.05
A50: 10544 | B50: VANS | C50: A6 | D50: 975 | E50: 6.85 | F50: =Tabla4[[#This Row],[CANTIDAD]]*Tabla4[[#This Row],[Costo Unitario]] -> 6678.75
A51: 7114 | B51: VANS SIN IMPRESON | C51: A4 | D51: 1968 | E51: 5.48 | F51: =Tabla4[[#This Row],[CANTIDAD]]*Tabla4[[#This Row],[Costo Unitario]] -> 10784.64 | G51: Factura Luis Felipe
A52: 7115 | B52: VANS SIN IMPRESON | C52: A5 | D52: 2190 | E52: 5.48 | F52: =Tabla4[[#This Row],[CANTIDAD]]*Tabla4[[#This Row],[Costo Unitario]] -> 12001.2 | G52: Factura Luis Felipe
A53: 7116 | B53: VANS SIN IMPRESON | C53: AO | D53: 1313 | E53: 5.48 | F53: =Tabla4[[#This Row],[CANTIDAD]]*Tabla4[[#This Row],[Costo Unitario]] -> 7195.24 | G53: Factura Luis Felipe
F54: =SUBTOTAL(109,Tabla4[Importe]) -> 463695.1
E57: =F54-E58 -> 135552.4
E58: =F2+F3+F13+F18+F27+F28+F29+F30+F31+F32+F33+F34+F35+F36+F37+F38+F39+F40+F41+F42+F43+F44+F45+F46+F48+F49+F50+F51+F52+F53 -> 328142.7

Sheet Agujeta
A1: MATERIAL | B1: MARCA | C1: CODIGO | D1: MEDIDA | E1: COLOR | F1: CANTIDAD FISCAL | G1: CANTIDAD | H1: Costo | I1: Importe | J1: OBS
A2: AGUJETA ALG | B2: SUPERGA | C2: 6162 | D2: 95 | E2: AMARILLO | F2: 91 | G2: 91 | H2: 2.62 | I2: =Tabla10[[#This Row],[CANTIDAD]]*Tabla10[[#This Row],[Costo ]] -> 238.42
A3: AGUJETA ALG | B3: SUPERGA | C3: 6154 | D3: 105 | E3: AMARILLO | F3: 44 | G3: 44 | H3: 2.62 | I3: =Tabla10[[#This Row],[CANTIDAD]]*Tabla10[[#This Row],[Costo ]] -> 115.28
A4: AGUJETA ALG | B4: SUPERGA | C4: 6171 | D4: 95 | E4: AZURE LT | F4: =2090-#REF!-#REF! -> #REF! | G4: 2090 | H4: 1.98 | I4: =Tabla10[[#This Row],[CANTIDAD]]*Tabla10[[#This Row],[Costo ]] -> 4138.2 | J4: Factura a Luis
A5: AGUJETA ALG | B5: SUPERGA | C5: 6175 | D5: 105 | E5: AZURE LT | F5: =2090-#REF!-#REF! -> #REF! | G5: 2090 | H5: 1.98 | I5: =Tabla10[[#This Row],[CANTIDAD]]*Tabla10[[#This Row],[Costo ]] -> 4138.2 | J5: Factura a Luis
A6: AGUJETA ALG | B6: SUPERGA | C6: 6180 | D6: 95 | E6: BEIGE ALMOND | F6: 188 | G6: 188 | H6: 1.98 | I6: =Tabla10[[#This Row],[CANTIDAD]]*Tabla10[[#This Row],[Costo ]] -> 372.24
A7: AGUJETA ALG | B7: SUPERGA | C7: 6185 | D7: 105 | E7: BEIGE ALMOND | F7: 42 | G7: 42 | H7: 1.98 | I7: =Tabla10[[#This Row],[CANTIDAD]]*Tabla10[[#This Row],[Costo ]] -> 83.16
A8: AGUJETA ALG | B8: SUPERGA | C8: 6052 | D8: 95 | E8: BLANCA | F8: 3250 | G8: 3250 | H8: 2.62 | I8: =Tabla10[[#This Row],[CANTIDAD]]*Tabla10[[#This Row],[Costo ]] -> 8515
A9: AGUJETA ALG | B9: SUPERGA | C9: 6150 | D9: 105 | E9: BLANCA | F9: =9000-#REF!-#REF! -> #REF! | G9: 6900 | H9: 2.62 | I9: =Tabla10[[#This Row],[CANTIDAD]]*Tabla10[[#This Row],[Costo ]] -> 18078 | J9: Factura a Luis
A10: AGUJETA ALG | B10: SUPERGA | C10: 6181 | D10: 95 | E10: GREY COLOMBA | F10: 114 | G10: 114 | H10: 1.98 | I10: =Tabla10[[#This Row],[CANTIDAD]]*Tabla10[[#This Row],[Costo ]] -> 225.72
A11: AGUJETA ALG | B11: SUPERGA | C11: 6184 | D11: 105 | E11: GREY COLOMBA | F11: 0 | H11: 1.98 | I11: =Tabla10[[#This Row],[CANTIDAD FISCAL]]*Tabla10[[#This Row],[Costo ]] -> 0 | M11: Solo un decimal en cantidad
A12: AGUJETA ALG | B12: SUPERGA | C12: 6159 | D12: 95 | E12: GREY SAG | F12: 438 | G12: 438 | H12: 2.62 | I12: =Tabla10[[#This Row],[CANTIDAD]]*Tabla10[[#This Row],[Costo ]] -> 1147.56
A13: AGUJETA ALG | B13: SUPERGA | C13: 6683 | D13: 105 | E13: GREY SAG | F13: 1560 | G13: 1560 | H13: 2.62 | I13: =Tabla10[[#This Row],[CANTIDAD]]*Tabla10[[#This Row],[Costo ]] -> 4087.2
A14: AGUJETA ALG | B14: SUPERGA | C14: 3232 | D14: 95 | E14: GREY SILVER | F14: 74 | G14: 74 | H14: 2.62 | I14: =Tabla10[[#This Row],[CANTIDAD]]*Tabla10[[#This Row],[Costo ]] -> 193.88
A15: AGUJETA ALG | B15: SUPERGA | C15: 6690 | D15: 105 | E15: GREY SILVER | F15: 51 | G15: 51 | H15: 2.62 | I15: =Tabla10[[#This Row],[CANTIDAD]]*Tabla10[[#This Row],[Costo ]] -> 133.62
A16: AGUJETA ALG | B16: SUPERGA | D16: 95 | E16: GRIS | F16: 50 | G16: 50 | H16: 2.62 | I16: =Tabla10[[#This Row],[CANTIDAD]]*Tabla10[[#This Row],[Costo ]] -> 131
A17: AGUJETA ALG | B17: SUPERGA | D17: 105 | E17: GRIS | F17: 16 | G17: 16 | H17: 2.62 | I17: =Tabla10[[#This Row],[CANTIDAD]]*Tabla10[[#This Row],[Costo ]] -> 41.92
A18: AGUJETA ALG | B18: SUPERGA | C18: 6173 | D18: 95 | E18: LT GREY | F18: 1500 | G18: 1500 | H18: 1.98 | I18: =Tabla10[[#This Row],[CANTIDAD]]*Tabla10[[#This Row],[Costo ]] -> 2970
A19: AGUJETA ALG | B19: SUPERGA | C19: 6177 | D19: 105 | E19: LT GREY | F19: 1496 | G19: 1496 | H19: 1.98 | I19: =Tabla10[[#This Row],[CANTIDAD]]*Tabla10[[#This Row],[Costo ]] -> 2962.08
A20: AGUJETA ALG | B20: SUPERGA | C20: 6092 | D20: 95 | E20: NAVY | F20: 156 | G20: 156 | H20: 2.62 | I20: =Tabla10[[#This Row],[CANTIDAD]]*Tabla10[[#This Row],[Costo ]] -> 408.72
A21: AGUJETA ALG | B21: SUPERGA | C21: 6682 | D21: 105 | E21: NAVY | F21: 960 | G21: 960 | H21: 2.62 | I21: =Tabla10[[#This Row],[CANTIDAD]]*Tabla10[[#This Row],[Costo ]] -> 2515.2
A22: AGUJETA ALG | B22: SUPERGA | C22: 6082 | D22: 95 | E22: NEGRA | F22: 1512 | G22: 1512 | H22: 2.62 | I22: =Tabla10[[#This Row],[CANTIDAD]]*Tabla10[[#This Row],[Costo ]] -> 3961.44
A23: AGUJETA ALG | B23: SUPERGA | C23: 6149 | D23: 105 | E23: NEGRA | F23: 726 | G23: 726 | H23: 2.62 | I23: =Tabla10[[#This Row],[CANTIDAD]]*Tabla10[[#This Row],[Costo ]] -> 1902.12
A24: AGUJETA ALG | B24: SUPERGA | C24: 6172 | D24: 95 | E24: PINK SKIN | F24: 590 | G24: 590 | H24: 1.98 | I24: =Tabla10[[#This Row],[CANTIDAD]]*Tabla10[[#This Row],[Costo ]] -> 1168.2
A25: AGUJETA ALG | B25: SUPERGA | C25: 6176 | D25: 105 | E25: PINK SKIN | F25: 590 | G25: 590 | H25: 1.98 | I25: =Tabla10[[#This Row],[CANTIDAD]]*Tabla10[[#This Row],[Costo ]] -> 1168.2
A26: AGUJETA ALG | B26: SUPERGA | C26: 6160 | D26: 95 | E26: ROJA | F26: 36 | G26: 36 | H26: 2.62 | I26: =Tabla10[[#This Row],[CANTIDAD]]*Tabla10[[#This Row],[Costo ]] -> 94.32
A27: AGUJETA ALG | B27: SUPERGA | C27: 6698 | D27: 105 | E27: ROJA | F27: 43 | G27: 43 | H27: 2.62 | I27: =Tabla10[[#This Row],[CANTIDAD]]*Tabla10[[#This Row],[Costo ]] -> 112.66
A28: AGUJETA ALG | B28: SUPERGA | D28: 95 | E28: ROSA | F28: 25 | G28: 25 | H28: 2.62 | I28: =Tabla10[[#This Row],[CANTIDAD]]*Tabla10[[#This Row],[Costo ]] -> 65.5
A29: AGUJETA ALG | B29: SUPERGA | D29: 95 | E29: VERDE JADE | F29: 33 | G29: 33 | H29: 2.62 | I29: =Tabla10[[#This Row],[CANTIDAD]]*Tabla10[[#This Row],[Costo ]] -> 86.46
A30: AGUJETA ALG | B30: SUPERGA | D30: 105 | E30: VERDE JADE | F30: 56 | G30: 56 | H30: 2.62 | I30: =Tabla10[[#This Row],[CANTIDAD]]*Tabla10[[#This Row],[Costo ]] -> 146.72
A31: AGUJETA ALG | B31: SUPERGA | C31: 6170 | D31: 95 | E31: WHITE AVORIO | F31: 1280 | G31: 1280 | H31: 1.98 | I31: =Tabla10[[#This Row],[CANTIDAD]]*Tabla10[[#This Row],[Costo ]] -> 2534.4
A32: AGUJETA ALG | B32: SUPERGA | C32: 6174 | D32: 105 | E32: WHITE AVORIO | F32: 1280 | G32: 1280 | H32: 1.98 | I32: =Tabla10[[#This Row],[CANTIDAD]]*Tabla10[[#This Row],[Costo ]] -> 2534.4
A33: AGUJETA AME F3 | B33: DC | C33: 6158 | D33: 90 | E33: 18127 GRIS PEWTER | F33: 246 | G33: 246 | H33: 1.98 | I33: =Tabla10[[#This Row],[CANTIDAD]]*Tabla10[[#This Row],[Costo ]] -> 487.08
A34: AGUJETA AME F3 | B34: DC | D34: 90 | E34: AZUL VIEJO | F34: 348 | G34: 348 | H34: 1.98 | I34: =Tabla10[[#This Row],[CANTIDAD]]*Tabla10[[#This Row],[Costo ]] -> 689.04
A35: AGUJETA AME F3 | B35: DC | D35: 90 | E35: BEIGE | F35: 550 | G35: 550 | H35: 1.98 | I35: =Tabla10[[#This Row],[CANTIDAD]]*Tabla10[[#This Row],[Costo ]] -> 1089
A36: AGUJETA AME F3 | B36: DC | C36: 6074 | D36: 90 | E36: BLANCA | F36: 288 | G36: 288 | H36: 1.98 | I36: =Tabla10[[#This Row],[CANTIDAD]]*Tabla10[[#This Row],[Costo ]] -> 570.24
A37: AGUJETA AME F3 | B37: DC | C37: 6120 | D37: 95 | E37: BLANCA | F37: 960 | G37: 960 | H37: 1.98 | I37: =Tabla10[[#This Row],[CANTIDAD]]*Tabla10[[#This Row],[Costo ]] -> 1900.8
A38: AGUJETA AME F3 | B38: DC | C38: 6186 | D38: 120 | E38: BLANCA | F38: 792 | G38: 792 | H38: 1.98 | I38: =Tabla10[[#This Row],[CANTIDAD]]*Tabla10[[#This Row],[Costo ]] -> 1568.16
A39: AGUJETA AME F3 | B39: DC | C39: 6012 | D39: 90 | E39: BLUE LIGHT MENTA | F39: 57 | G39: 57 | H39: 1.98 | I39: =Tabla10[[#This Row],[CANTIDAD]]*Tabla10[[#This Row],[Costo ]] -> 112.86
A40: AGUJETA AME F3 | B40: DC | C40: 6122 | D40: 95 | E40: BLUE LIGHT MENTA | F40: 1075 | G40: 1075 | H40: 1.98 | I40: =Tabla10[[#This Row],[CANTIDAD]]*Tabla10[[#This Row],[Costo ]] -> 2128.5
A41: AGUJETA AME F3 | B41: DC | D41: 90 | E41: BLUE MIRAGE | F41: 440 | G41: 440 | H41: 1.98 | I41: =Tabla10[[#This Row],[CANTIDAD]]*Tabla10[[#This Row],[Costo ]] -> 871.2
A42: AGUJETA AME F3 | B42: DC | C42: 6148 | D42: 90 | E42: CEREZA | F42: 261 | G42: 261 | H42: 1.98 | I42: =Tabla10[[#This Row],[CANTIDAD]]*Tabla10[[#This Row],[Costo ]] -> 516.78
A43: AGUJETA AME F3 | B43: DC | C43: 10215 | D43: 95 | E43: CEREZA 424 CHILLI PEPPER | F43: 212 | G43: 212 | H43: 1.98 | I43: =Tabla10[[#This Row],[CANTIDAD]]*Tabla10[[#This Row],[Costo ]] -> 419.76
A44: AGUJETA AME F3 | B44: DC | C44: 6093 | D44: 90 | E44: CORAL FOSFORESENTE | F44: 0 | H44: 1.98 | I44: =Tabla10[[#This Row],[CANTIDAD FISCAL]]*Tabla10[[#This Row],[Costo ]] -> 0
A45: AGUJETA AME F3 | B45: DC | D45: 90 | E45: CREMA | F45: 0 | H45: 1.98 | I45: =Tabla10[[#This Row],[CANTIDAD FISCAL]]*Tabla10[[#This Row],[Costo ]] -> 0
A46: AGUJETA AME F3 | B46: DC | D46: 95 | E46: GRIS | F46: 2136 | G46: 2136 | H46: 1.98 | I46: =Tabla10[[#This Row],[CANTIDAD]]*Tabla10[[#This Row],[Costo ]] -> 4229.28
A47: AGUJETA AME F3 | B47: DC | C47: 6155 | D47: 95 | E47: GRIS NIMBO | F47: 612 | G47: 612 | H47: 1.98 | I47: =Tabla10[[#This Row],[CANTIDAD]]*Tabla10[[#This Row],[Costo ]] -> 1211.76
A48: AGUJETA AME F3 | B48: DC | C48: 6151 | D48: 90 | E48: GRIS NIMBO | F48: 395 | G48: 395 | H48: 1.98 | I48: =Tabla10[[#This Row],[CANTIDAD]]*Tabla10[[#This Row],[Costo ]] -> 782.1
A49: AGUJETA AME F3 | B49: DC | D49: 90 | E49: GRIS OXFORD | F49: 0 | H49: 1.98 | I49: =Tabla10[[#This Row],[CANTIDAD FISCAL]]*Tabla10[[#This Row],[Costo ]] -> 0
A50: AGUJETA AME F3 | B50: DC | C50: 6080 | D50: 95 | E50: GRIS PEWTEE | F50: 466 | G50: 466 | H50: 1.98 | I50: =Tabla10[[#This Row],[CANTIDAD]]*Tabla10[[#This Row],[Costo ]] -> 922.68
A51: AGUJETA AME F3 | B51: DC | C51: 6012 | D51: 90 | E51: JADE MOONLIGTH | F51: 0 | H51: 1.98 | I51: =Tabla10[[#This Row],[CANTIDAD FISCAL]]*Tabla10[[#This Row],[Costo ]] -> 0
A52: AGUJETA AME F3 | B52: DC | D52: 90 | E52: KAKI | F52: 720 | G52: 720 | H52: 1.98 | I52: =Tabla10[[#This Row],[CANTIDAD]]*Tabla10[[#This Row],[Costo ]] -> 1425.6
A53: AGUJETA AME F3 | B53: DC | D53: 95 | E53: KAKI | F53: 650 | G53: 650 | H53: 1.98 | I53: =Tabla10[[#This Row],[CANTIDAD]]*Tabla10[[#This Row],[Costo ]] -> 1287
A54: AGUJETA AME F3 | B54: DC | C54: 6166 | D54: 90 | E54: KAKI1071 (INCENSE) | F54: 72 | G54: 72 | H54: 1.98 | I54: =Tabla10[[#This Row],[CANTIDAD]]*Tabla10[[#This Row],[Costo ]] -> 142.56
A55: AGUJETA AME F3 | B55: DC | C55: 6164 | D55: 95 | E55: KAKI1071 (INCENSE) | F55: 201 | G55: 201 | H55: 1.98 | I55: =Tabla10[[#This Row],[CANTIDAD]]*Tabla10[[#This Row],[Costo ]] -> 397.98
A56: AGUJETA AME F3 | B56: DC | D56: 90 | E56: MALVA OCASO | F56: 341 | G56: 341 | H56: 1.98 | I56: =Tabla10[[#This Row],[CANTIDAD]]*Tabla10[[#This Row],[Costo ]] -> 675.18
A57: AGUJETA AME F3 | B57: DC | D57: 95 | E57: MALVA OCASO | F57: 79 | G57: 79 | H57: 1.98 | I57: =Tabla10[[#This Row],[CANTIDAD]]*Tabla10[[#This Row],[Costo ]] -> 156.42
A58: AGUJETA AME F3 | B58: DC | C58: 6061 | D58: 95 | E58: MARINO (AZMN04) BLACK IRIS | F58: 0 | H58: 1.98 | I58: =Tabla10[[#This Row],[CANTIDAD FISCAL]]*Tabla10[[#This Row],[Costo ]] -> 0
A59: AGUJETA AME F3 | B59: DC | C59: 10211 | D59: 95 | E59: MOTHER OF PEARL | F59: 0 | H59: 1.98 | I59: =Tabla10[[#This Row],[CANTIDAD FISCAL]]*Tabla10[[#This Row],[Costo ]] -> 0
A60: AGUJETA AME F3 | B60: DC | C60: 6075 | D60: 90 | E60: NEGRA | F60: 1400 | G60: 1400 | H60: 1.98 | I60: =Tabla10[[#This Row],[CANTIDAD]]*Tabla10[[#This Row],[Costo ]] -> 2772
A61: AGUJETA AME F3 | B61: DC | C61: 6121 | D61: 95 | E61: NEGRA | F61: 744 | G61: 744 | H61: 1.98 | I61: =Tabla10[[#This Row],[CANTIDAD]]*Tabla10[[#This Row],[Costo ]] -> 1473.12
A62: AGUJETA AME F3 | B62: DC | C62: 6075 | D62: 120 | E62: NEGRA | F62: 461 | G62: 461 | H62: 1.98 | I62: =Tabla10[[#This Row],[CANTIDAD]]*Tabla10[[#This Row],[Costo ]] -> 912.78
A63: AGUJETA AME F3 | B63: DC | D63: 90 | E63: OSTION | F63: 328 | G63: 328 | H63: 1.98 | I63: =Tabla10[[#This Row],[CANTIDAD]]*Tabla10[[#This Row],[Costo ]] -> 649.44
A64: AGUJETA AME F3 | B64: DC | C64: 10623 | D64: 95 | E64: OSTION | F64: 1472 | G64: 1472 | H64: 1.98 | I64: =Tabla10[[#This Row],[CANTIDAD]]*Tabla10[[#This Row],[Costo ]] -> 2914.56
A65: AGUJETA AME F3 | B65: DC | C65: 6024 | D65: 90 | E65: PLANA (17-1505 TPG) QUAIL | F65: 147 | G65: 147 | H65: 1.98 | I65: =Tabla10[[#This Row],[CANTIDAD]]*Tabla10[[#This Row],[Costo ]] -> 291.06
A66: AGUJETA AME F3 | B66: DC | C66: 6022 | D66: 90 | E66: PLANA PASTEL LILAC(14-3812 TPG) | F66: 341 | G66: 341 | H66: 1.98 | I66: =Tabla10[[#This Row],[CANTIDAD]]*Tabla10[[#This Row],[Costo ]] -> 675.18
A67: AGUJETA AME F3 | B67: DC | C67: 10212 | D67: 95 | E67: PLANA PASTEL LILAC(14-3812 TPG) | F67: 95 | G67: 95 | H67: 1.98 | I67: =Tabla10[[#This Row],[CANTIDAD]]*Tabla10[[#This Row],[Costo ]] -> 188.1
A68: AGUJETA AME F3 | B68: DC | C68: 10216 | D68: 95 | E68: PLANA QUAIL (MALVAOCASO1911) | F68: 29 | G68: 29 | H68: 1.98 | I68: =Tabla10[[#This Row],[CANTIDAD]]*Tabla10[[#This Row],[Costo ]] -> 57.42
A69: AGUJETA AME F3 | B69: DC | C69: 6113 | D69: 90 | E69: POROTEL LILAC | F69: 128 | G69: 128 | H69: 1.98 | I69: =Tabla10[[#This Row],[CANTIDAD]]*Tabla10[[#This Row],[Costo ]] -> 253.44
A70: AGUJETA AME F3 | B70: DC | D70: 95 | E70: POROTEL LILAC | F70: 180 | G70: 180 | H70: 1.98 | I70: =Tabla10[[#This Row],[CANTIDAD]]*Tabla10[[#This Row],[Costo ]] -> 356.4
A71: AGUJETA AME F3 | B71: DC | C71: 6076 | D71: 90 | E71: ROSA CARMINO | F71: 544 | G71: 544 | H71: 1.98 | I71: =Tabla10[[#This Row],[CANTIDAD]]*Tabla10[[#This Row],[Costo ]] -> 1077.12
A72: AGUJETA AME F3 | B72: DC | D72: 95 | E72: ROSA CARMINO | F72: 157 | G72: 157 | H72: 1.98 | I72: =Tabla10[[#This Row],[CANTIDAD]]*Tabla10[[#This Row],[Costo ]] -> 310.86
A73: AGUJETA AME F3 | B73: DC | C73: 6147 | D73: 90 | E73: ROSA CREPE | F73: 360 | G73: 360 | H73: 1.98 | I73: =Tabla10[[#This Row],[CANTIDAD]]*Tabla10[[#This Row],[Costo ]] -> 712.8
A74: AGUJETA AME F3 | B74: DC | C74: 10214 | D74: 95 | E74: ROSA CREPE | F74: 360 | G74: 360 | H74: 1.98 | I74: =Tabla10[[#This Row],[CANTIDAD]]*Tabla10[[#This Row],[Costo ]] -> 712.8
A75: AGUJETA AME F3 | B75: DC | C75: 10214 | D75: 95 | E75: ROSA CREPE18144 CORAL ALMOND | F75: 740 | G75: 740 | H75: 1.98 | I75: =Tabla10[[#This Row],[CANTIDAD]]*Tabla10[[#This Row],[Costo ]] -> 1465.2
A76: AGUJETA AME F3 | B76: DC | C76: 6156 | D76: 95 | E76: ROSA VIEJO2028 OLD DC ROSE | F76: 316 | G76: 316 | H76: 1.98 | I76: =Tabla10[[#This Row],[CANTIDAD]]*Tabla10[[#This Row],[Costo ]] -> 625.68
A77: AGUJETA AME F3 | B77: DC | C77: 6157 | D77: 90 | E77: ROSA VIEJO2028 OLD ROSE | F77: 460 | G77: 460 | H77: 1.98 | I77: =Tabla10[[#This Row],[CANTIDAD]]*Tabla10[[#This Row],[Costo ]] -> 910.8
A78: AGUJETA AME F3 | B78: DC | D78: 90 | E78: SUDAN BROWN | F78: 0 | H78: 1.98 | I78: =Tabla10[[#This Row],[CANTIDAD FISCAL]]*Tabla10[[#This Row],[Costo ]] -> 0
A79: AGUJETA AME F3 | B79: DC | C79: 6090 | D79: 95 | E79: SUDAN BROWN | F79: 0 | H79: 1.98 | I79: =Tabla10[[#This Row],[CANTIDAD FISCAL]]*Tabla10[[#This Row],[Costo ]] -> 0
A80: AGUJETA AME F3 | B80: DC | C80: 6117 | D80: 90 | E80: VERDE PISTACHE | F80: 185 | G80: 185 | H80: 1.98 | I80: =Tabla10[[#This Row],[CANTIDAD]]*Tabla10[[#This Row],[Costo ]] -> 366.3
A81: AGUJETA AME F3 | B81: DC | D81: 95 | E81: VERDE PISTACHE | F81: 224 | G81: 224 | H81: 1.98 | I81: =Tabla10[[#This Row],[CANTIDAD]]*Tabla10[[#This Row],[Costo ]] -> 443.52
A82: AGUJETA AMERICANA | C82: 6321 | D82: 70 | E82: AZUL MARINO | F82: 1080 | G82: 1080 | H82: 1.98 | I82: =Tabla10[[#This Row],[CANTIDAD]]*Tabla10[[#This Row],[Costo ]] -> 2138.4
A83: AGUJETA AMERICANA | C83: 6048 | D83: 80 | E83: AZUL MARINO | F83: 2045 | G83: 2045 | H83: 1.98 | I83: =Tabla10[[#This Row],[CANTIDAD]]*Tabla10[[#This Row],[Costo ]] -> 4049.1
A84: AGUJETA AMERICANA | C84: 6057 | D84: 90 | E84: AZUL MARINO | F84: 0 | H84: 1.98 | I84: =Tabla10[[#This Row],[CANTIDAD FISCAL]]*Tabla10[[#This Row],[Costo ]] -> 0
A85: AGUJETA AMERICANA | C85: 6325 | D85: 100 | E85: AZUL MARINO | F85: 535 | G85: 535 | H85: 1.98 | I85: =Tabla10[[#This Row],[CANTIDAD]]*Tabla10[[#This Row],[Costo ]] -> 1059.3
A86: AGUJETA AMERICANA | C86: 6020 | D86: 120 | E86: AZUL MARINO | F86: 27 | G86: 27 | H86: 1.98 | I86: =Tabla10[[#This Row],[CANTIDAD]]*Tabla10[[#This Row],[Costo ]] -> 53.46
A87: AGUJETA AMERICANA | C87: 6038 | D87: 140 | E87: AZUL MARINO | F87: 1230 | G87: 1230 | H87: 1.98 | I87: =Tabla10[[#This Row],[CANTIDAD]]*Tabla10[[#This Row],[Costo ]] -> 2435.4
A88: AGUJETA AMERICANA | C88: 6179 | D88: 150 | E88: AZUL MARINO | F88: 2042 | G88: 2042 | H88: 1.98 | I88: =Tabla10[[#This Row],[CANTIDAD]]*Tabla10[[#This Row],[Costo ]] -> 4043.16
A89: AGUJETA AMERICANA | C89: 6341 | D89: 70 | E89: AZUL REY | F89: 1293 | G89: 1293 | H89: 1.98 | I89: =Tabla10[[#This Row],[CANTIDAD]]*Tabla10[[#This Row],[Costo ]] -> 2560.14
A90: AGUJETA AMERICANA | C90: 6047 | D90: 80 | E90: AZUL REY | F90: 547 | G90: 547 | H90: 1.98 | I90: =Tabla10[[#This Row],[CANTIDAD]]*Tabla10[[#This Row],[Costo ]] -> 1083.06
A91: AGUJETA AMERICANA | C91: 6055 | D91: 90 | E91: AZUL REY | F91: 1200 | G91: 1200 | H91: 1.98 | I91: =Tabla10[[#This Row],[CANTIDAD]]*Tabla10[[#This Row],[Costo ]] -> 2376
A92: AGUJETA AMERICANA | C92: 6347 | D92: 120 | E92: AZUL REY | F92: 1148 | G92: 1148 | H92: 1.98 | I92: =Tabla10[[#This Row],[CANTIDAD]]*Tabla10[[#This Row],[Costo ]] -> 2273.04
A93: AGUJETA AMERICANA | C93: 6301 | D93: 70 | E93: BLANCA | F93: 0 | H93: 1.98 | I93: =Tabla10[[#This Row],[CANTIDAD FISCAL]]*Tabla10[[#This Row],[Costo ]] -> 0
A94: AGUJETA AMERICANA | C94: 6015 | D94: 80 | E94: BLANCA | F94: 0 | H94: 1.98 | I94: =Tabla10[[#This Row],[CANTIDAD FISCAL]]*Tabla10[[#This Row],[Costo ]] -> 0
A95: AGUJETA AMERICANA | C95: 6017 | D95: 90 | E95: BLANCA | F95: 18900 | G95: 18900 | H95: 1.98 | I95: =Tabla10[[#This Row],[CANTIDAD]]*Tabla10[[#This Row],[Costo ]] -> 37422
A96: AGUJETA AMERICANA | C96: 6018 | D96: 100 | E96: BLANCA | F96: 0 | H96: 1.98 | I96: =Tabla10[[#This Row],[CANTIDAD FISCAL]]*Tabla10[[#This Row],[Costo ]] -> 0
A97: AGUJETA AMERICANA | C97: 6029 | D97: 110 | E97: BLANCA | F97: 4800 | G97: 4800 | H97: 1.98 | I97: =Tabla10[[#This Row],[CANTIDAD]]*Tabla10[[#This Row],[Costo ]] -> 9504
A98: AGUJETA AMERICANA | C98: 6050 | D98: 120 | E98: BLANCA | F98: 0 | H98: 1.98 | I98: =Tabla10[[#This Row],[CANTIDAD FISCAL]]*Tabla10[[#This Row],[Costo ]] -> 0
A99: AGUJETA AMERICANA | C99: 6050 | D99: 120 | E99: BLANCA | F99: 0 | H99: 1.98 | I99: =Tabla10[[#This Row],[CANTIDAD FISCAL]]*Tabla10[[#This Row],[Costo ]] -> 0
A100: AGUJETA AMERICANA | C100: 6051 | D100: 140 | E100: BLANCA | F100: 4744 | G100: 4744 | H100: 1.98 | I100: =Tabla10[[#This Row],[CANTIDAD]]*Tabla10[[#This Row],[Costo ]] -> 9393.12
...

Sheet Caja_Embarque
F1: PRECIO NO INCLUYE IVA
A2: # Material | B2: Proveedor | C2: CAJA | D2: MEDIDAS | E2: COSTO | F2: USADA EN: | G2: CANTIDAD | H2: Prs/Caja | I2: En Pares | J2: Importe | K2: OBS
B3: Imagen en Cartón | C3: AE-12P | E3: 18.37 | F3: Ae Niña (AEK), cajas combinadas 18/21 y 2/5 | G3: 134 | H3: 12 | I3: =Tabla5[[#This Row],[CANTIDAD]]*Tabla5[[#This Row],[Prs/Caja]] -> 1608 | J3: =Tabla5[[#This Row],[COSTO]]*Tabla5[[#This Row],[CANTIDAD]] -> 2461.58
A4: 7030 | B4: Imagen en Cartón | C4: ES2 | D4: 42*40*37.8 | E4: 26.89 | F4: AE CABALLERO1 ó Combinadas (caballero 1 y 2) / AIRWALK | G4: 0 | H4: 6 | I4: =Tabla5[[#This Row],[CANTIDAD]]*Tabla5[[#This Row],[Prs/Caja]] -> 0 | J4: =Tabla5[[#This Row],[COSTO]]*Tabla5[[#This Row],[CANTIDAD]] -> 0
A5: 7052 | B5: Imagen en Cartón | C5: C-1 | D5: 44*42*30 | E5: 18.2 | F5: Utilizada para caja chancleta de Price Shoes | G5: 163 | H5: 12 | I5: =Tabla5[[#This Row],[CANTIDAD]]*Tabla5[[#This Row],[Prs/Caja]] -> 1956 | J5: =Tabla5[[#This Row],[COSTO]]*Tabla5[[#This Row],[CANTIDAD]] -> 2966.6
A6: 7053 | B6: Imagen en Cartón | C6: C-2 | D6: 66.7*52.2*35.3 | E6: 28.71 | F6: Utilizada para caja caballero de Price Shoes | G6: 39 | H6: 12 | I6: =Tabla5[[#This Row],[CANTIDAD]]*Tabla5[[#This Row],[Prs/Caja]] -> 468 | J6: =Tabla5[[#This Row],[COSTO]]*Tabla5[[#This Row],[CANTIDAD]] -> 1119.69
B7: Imagen en Cartón | C7: Polo 12P | D7: 65*34.4*31 | E7: 20.08 | F7: Utilizada sólo en marca Polo | G7: 14 | H7: 12 | I7: =Tabla5[[#This Row],[CANTIDAD]]*Tabla5[[#This Row],[Prs/Caja]] -> 168 | J7: =Tabla5[[#This Row],[COSTO]]*Tabla5[[#This Row],[CANTIDAD]] -> 281.12
A8: 7112 | B8: Imagen en Cartón | C8: Náutica 12P | D8: 58.2*49.8*31.5 | E8: 26.97 | F8: Utilizada sólo en marca Náutica | G8: 0 | H8: 12 | I8: =Tabla5[[#This Row],[CANTIDAD]]*Tabla5[[#This Row],[Prs/Caja]] -> 0 | J8: =Tabla5[[#This Row],[COSTO]]*Tabla5[[#This Row],[CANTIDAD]] -> 0
A9: 7002 | B9: Imagen en Cartón | C9: DC/Chica | D9: 57.2*48.5*29.8 | E9: 28.83 | F9: DC/CHICA | G9: 45 | H9: 12 | I9: =Tabla5[[#This Row],[CANTIDAD]]*Tabla5[[#This Row],[Prs/Caja]] -> 540 | J9: =Tabla5[[#This Row],[COSTO]]*Tabla5[[#This Row],[CANTIDAD]] -> 1297.35
A10: 7005 | B10: Imagen en Cartón | C10: DC/Grande | D10: 59.8*50*33.8 | E10: 34.7 | F10: * DC/Grande ó combinadas (DC-Chica y DC-Grande) * Náutica 10 prs en medida 33 x 22 x 12 cm | G10: 41 | H10: 12 | I10: =Tabla5[[#This Row],[CANTIDAD]]*Tabla5[[#This Row],[Prs/Caja]] -> 492 | J10: =Tabla5[[#This Row],[COSTO]]*Tabla5[[#This Row],[CANTIDAD]] -> 1422.7
A11: 7021 | B11: Imagen en Cartón | C11: HD6P | D11: 42.4*36.2*36 | E11: 27.88 | F11: HD CAJA MEDIANA | H11: 6 | I11: =Tabla5[[#This Row],[CANTIDAD]]*Tabla5[[#This Row],[Prs/Caja]] -> 0 | J11: =Tabla5[[#This Row],[COSTO]]*Tabla5[[#This Row],[CANTIDAD]] -> 0
A12: 7051 | B12: Imagen en Cartón | C12: HD26P | D12: 44.2*40.2*37.2 | E12: 30.43 | F12: Harley davidson grande (6prs) y Caja Grande Superga (7 prs) | H12: 6 | I12: =Tabla5[[#This Row],[CANTIDAD]]*Tabla5[[#This Row],[Prs/Caja]] -> 0 | J12: =Tabla5[[#This Row],[COSTO]]*Tabla5[[#This Row],[CANTIDAD]] -> 0
A13: 7113 | B13: Imagen en Cartón | C13: HD36P | D13: 48.3*38.2*36.1 | E13: 32.46 | F13: Harley davidson XG (6prs) | H13: 6 | I13: =Tabla5[[#This Row],[CANTIDAD]]*Tabla5[[#This Row],[Prs/Caja]] -> 0 | J13: =Tabla5[[#This Row],[COSTO]]*Tabla5[[#This Row],[CANTIDAD]] -> 0
A14: 7049 | B14: Imagen en Cartón | C14: SUPERGA CHICA | D14: 53.5*46.2*32 | E14: 35.06 | F14: 12 PARES SUPERGA (CAJA CHICA) | G14: 76 | H14: 12 | I14: =Tabla5[[#This Row],[CANTIDAD]]*Tabla5[[#This Row],[Prs/Caja]] -> 912 | J14: =Tabla5[[#This Row],[COSTO]]*Tabla5[[#This Row],[CANTIDAD]] -> 2664.56
A15: 7050 | B15: Imagen en Cartón | C15: SUPERGA GRANDE | D15: 53.5*46.2*34.8 | E15: 36.36 | F15: 12 PARES SUPERGA (CAJA MEDIANA) | G15: 270 | H15: 12 | I15: =Tabla5[[#This Row],[CANTIDAD]]*Tabla5[[#This Row],[Prs/Caja]] -> 3240 | J15: =Tabla5[[#This Row],[COSTO]]*Tabla5[[#This Row],[CANTIDAD]] -> 9817.2
B16: Imagen en Cartón | C16: SUPERGA CHICA (nva medida) | D16: 47*47*31.4 | E16: 29.85 | F16: 12 PARES SUPERGA (CAJA CHICA) | G16: 0 | H16: 12 | I16: =Tabla5[[#This Row],[CANTIDAD]]*Tabla5[[#This Row],[Prs/Caja]] -> 0 | J16: =Tabla5[[#This Row],[COSTO]]*Tabla5[[#This Row],[CANTIDAD]] -> 0
B17: Imagen en Cartón | C17: SUPERGA GRANDE (nva medida) | D17: 49.8*49.8*34 | E17: 35.01 | F17: 12 PARES SUPERGA (CAJA MEDIANA) | G17: 24 | H17: 12 | I17: =Tabla5[[#This Row],[CANTIDAD]]*Tabla5[[#This Row],[Prs/Caja]] -> 288 | J17: =Tabla5[[#This Row],[COSTO]]*Tabla5[[#This Row],[CANTIDAD]] -> 840.24
C18: Superga Plataforma | D18: 63*38.4*67.4 | E18: 46.71 | F18: SUPERGA PLATAFORMA | G18: 63 | H18: 12 | I18: =Tabla5[[#This Row],[CANTIDAD]]*Tabla5[[#This Row],[Prs/Caja]] -> 756 | J18: =Tabla5[[#This Row],[COSTO]]*Tabla5[[#This Row],[CANTIDAD]] -> 2942.73
B19: CartoEmpaques | C19: KEEN SMALL | D19: 51*47.5*31.5 | E19: 34.8 | F19: SÓLO KEEN | G19: 98 | H19: 0 | I19: =Tabla5[[#This Row],[CANTIDAD]]*Tabla5[[#This Row],[Prs/Caja]] -> 0 | J19: =Tabla5[[#This Row],[COSTO]]*Tabla5[[#This Row],[CANTIDAD]] -> 3410.4 | K19: Utilizada para 2das Vans
B20: CartoEmpaques | C20: KEEN MEDIUM | D20: 55.8*49.8*34 | E20: 39.42 | F20: SÓLO KEEN | G20: 0 | H20: 0 | I20: =Tabla5[[#This Row],[CANTIDAD]]*Tabla5[[#This Row],[Prs/Caja]] -> 0 | J20: =Tabla5[[#This Row],[COSTO]]*Tabla5[[#This Row],[CANTIDAD]] -> 0 | K20: Utilizada para 2das Vans
B21: CartoEmpaques | C21: KEEN LARGE | D21: 60*51.5*36.5 | E21: 43.59 | F21: SÓLO KEEN | G21: 12 | H21: 0 | I21: =Tabla5[[#This Row],[CANTIDAD]]*Tabla5[[#This Row],[Prs/Caja]] -> 0 | J21: =Tabla5[[#This Row],[COSTO]]*Tabla5[[#This Row],[CANTIDAD]] -> 523.08 | K21: Utilizada para 2das Vans
B22: Imagen en Cartón | C22: Skechers 1 (10½ al 12½) | D22: 51.2*38.7*25.5 | E22: 23.43 | F22: SÓLO SKECHERS NIÑOS | G22: 0 | H22: 12 | I22: =Tabla5[[#This Row],[CANTIDAD]]*Tabla5[[#This Row],[Prs/Caja]] -> 0 | J22: =Tabla5[[#This Row],[COSTO]]*Tabla5[[#This Row],[CANTIDAD]] -> 0
B23: Imagen en Cartón | C23: Skechers 2 (13, 13½, 1, 1½) | D23: 50.8*45.2*28.2 | E23: 24.12 | F23: SÓLO SKECHERS NIÑOS | G23: 73 | H23: 12 | I23: =Tabla5[[#This Row],[CANTIDAD]]*Tabla5[[#This Row],[Prs/Caja]] -> 876 | J23: =Tabla5[[#This Row],[COSTO]]*Tabla5[[#This Row],[CANTIDAD]] -> 1760.76
B24: Imagen en Cartón | C24: Skechers 3 (2 al 3) | D24: 51.2*42*28.8 | E24: 26.87 | F24: SÓLO SKECHERS NIÑOS | G24: 135 | H24: 12 | I24: =Tabla5[[#This Row],[CANTIDAD]]*Tabla5[[#This Row],[Prs/Caja]] -> 1620 | J24: =Tabla5[[#This Row],[COSTO]]*Tabla5[[#This Row],[CANTIDAD]] -> 3627.45
B25: Imagen en Cartón | C25: Skechers 4 (3½ al 5) | D25: 52.5*48.5*30.8 | E25: 28.87 | F25: SÓLO SKECHERS NIÑOS | G25: 15 | H25: 12 | I25: =Tabla5[[#This Row],[CANTIDAD]]*Tabla5[[#This Row],[Prs/Caja]] -> 180 | J25: =Tabla5[[#This Row],[COSTO]]*Tabla5[[#This Row],[CANTIDAD]] -> 433.05
B26: Imagen en Cartón | C26: Skechers 5 (5½ al 7) | D26: 55*48.5*33.4 | E26: 33.36 | F26: SÓLO SKECHERS NIÑOS | G26: 40 | H26: 12 | I26: =Tabla5[[#This Row],[CANTIDAD]]*Tabla5[[#This Row],[Prs/Caja]] -> 480 | J26: =Tabla5[[#This Row],[COSTO]]*Tabla5[[#This Row],[CANTIDAD]] -> 1334.4
B27: Imagen en Cartón | C27: SK6 6prs_Chica | D27: 41.4*34.31.6 | E27: 21.53 | F27: SÓLO SKECHERS COCINA | G27: 44 | H27: 6 | I27: =Tabla5[[#This Row],[CANTIDAD]]*Tabla5[[#This Row],[Prs/Caja]] -> 264 | J27: =Tabla5[[#This Row],[COSTO]]*Tabla5[[#This Row],[CANTIDAD]] -> 947.32
B28: Imagen en Cartón | C28: SK7 6prs_Grande | D28: 49*39*37.5 | E28: 32.94 | F28: SÓLO SKECHERS COCINA | G28: 43 | H28: 6 | I28: =Tabla5[[#This Row],[CANTIDAD]]*Tabla5[[#This Row],[Prs/Caja]] -> 258 | J28: =Tabla5[[#This Row],[COSTO]]*Tabla5[[#This Row],[CANTIDAD]] -> 1416.42
B29: Imagen en Cartón | C29: SK8 12 prs / Grande | D29: 72.8*51.5*37.5 | E29: 42.2 | F29: SÓLO SKECHERS COCINA | G29: 76 | H29: 12 | I29: =Tabla5[[#This Row],[CANTIDAD]]*Tabla5[[#This Row],[Prs/Caja]] -> 912 | J29: =Tabla5[[#This Row],[COSTO]]*Tabla5[[#This Row],[CANTIDAD]] -> 3207.2 | K29: YA NO SE UTILIZA
B30: Imagen en Cartón | C30: Skechers Niña1 | D30: 46.5*33.4*20.4 | E30: 17.05 | F30: SÓLO SKECHERS | G30: 136 | H30: 12 | I30: =Tabla5[[#This Row],[CANTIDAD]]*Tabla5[[#This Row],[Prs/Caja]] -> 1632 | J30: =Tabla5[[#This Row],[COSTO]]*Tabla5[[#This Row],[CANTIDAD]] -> 2318.8 | K30: YA NO SE UTILIZA
B31: Imagen en Cartón | C31: Skechers Niña2 | D31: 48*37*23 | E31: 18.63 | F31: SÓLO SKECHERS | G31: 46 | H31: 12 | I31: =Tabla5[[#This Row],[CANTIDAD]]*Tabla5[[#This Row],[Prs/Caja]] -> 552 | J31: =Tabla5[[#This Row],[COSTO]]*Tabla5[[#This Row],[CANTIDAD]] -> 856.98 | K31: YA NO SE UTILIZA
B32: AlfaPaq | C32: Blanx Chica | E32: 42.996 | F32: SÓLO BLANX | G32: 423 | H32: 12 | I32: =Tabla5[[#This Row],[CANTIDAD]]*Tabla5[[#This Row],[Prs/Caja]] -> 5076 | J32: =Tabla5[[#This Row],[COSTO]]*Tabla5[[#This Row],[CANTIDAD]] -> 18187.308 | K32: Inventario de cliente
B33: AlfaPaq | C33: Blanx Grande | E33: 43.29 | F33: SÓLO BLANX | G33: 19 | H33: 14 | I33: =Tabla5[[#This Row],[CANTIDAD]]*Tabla5[[#This Row],[Prs/Caja]] -> 266 | J33: =Tabla5[[#This Row],[COSTO]]*Tabla5[[#This Row],[CANTIDAD]] -> 822.51 | K33: Inventario de cliente
A34: 7097 | B34: Imagen en Cartón | C34: A4-6 | E34: 13.33 | F34: VANS | G34: 0 | H34: 6 | I34: =Tabla5[[#This Row],[CANTIDAD]]*Tabla5[[#This Row],[Prs/Caja]] -> 0 | J34: =Tabla5[[#This Row],[COSTO]]*Tabla5[[#This Row],[CANTIDAD]] -> 0
A35: 7101 | B35: Imagen en Cartón | C35: A4-12 | E35: 22.1 | F35: VANS | G35: 90 | H35: 12 | I35: =Tabla5[[#This Row],[CANTIDAD]]*Tabla5[[#This Row],[Prs/Caja]] -> 1080 | J35: =Tabla5[[#This Row],[COSTO]]*Tabla5[[#This Row],[CANTIDAD]] -> 1989
A36: 7100 | B36: Imagen en Cartón | C36: A5-6 | E36: 15.64 | F36: VANS | G36: 31 | H36: 6 | I36: =Tabla5[[#This Row],[CANTIDAD]]*Tabla5[[#This Row],[Prs/Caja]] -> 186 | J36: =Tabla5[[#This Row],[COSTO]]*Tabla5[[#This Row],[CANTIDAD]] -> 484.84
A37: 7102 | B37: Imagen en Cartón | C37: A5-12 | E37: 25.87 | F37: VANS | G37: 29 | H37: 12 | I37: =Tabla5[[#This Row],[CANTIDAD]]*Tabla5[[#This Row],[Prs/Caja]] -> 348 | J37: =Tabla5[[#This Row],[COSTO]]*Tabla5[[#This Row],[CANTIDAD]] -> 750.23
A38: 7098 | B38: Imagen en Cartón | C38: A0-6 | E38: 17.32 | F38: VANS | G38: 7 | H38: 6 | I38: =Tabla5[[#This Row],[CANTIDAD]]*Tabla5[[#This Row],[Prs/Caja]] -> 42 | J38: =Tabla5[[#This Row],[COSTO]]*Tabla5[[#This Row],[CANTIDAD]] -> 121.24
A39: 7103 | B39: Imagen en Cartón | C39: A0-12 | E39: 28.63 | F39: VANS / GOODYEAR (Price Shoes) | G39: 16 | H39: 12 | I39: =Tabla5[[#This Row],[CANTIDAD]]*Tabla5[[#This Row],[Prs/Caja]] -> 192 | J39: =Tabla5[[#This Row],[COSTO]]*Tabla5[[#This Row],[CANTIDAD]] -> 458.08
A40: 7099 | B40: Imagen en Cartón | C40: A6-6 | E40: 20.11 | F40: VANS | G40: 35 | H40: 6 | I40: =Tabla5[[#This Row],[CANTIDAD]]*Tabla5[[#This Row],[Prs/Caja]] -> 210 | J40: =Tabla5[[#This Row],[COSTO]]*Tabla5[[#This Row],[CANTIDAD]] -> 703.85
A41: 7104 | B41: Imagen en Cartón | C41: A6-12 | E41: 30.09 | F41: VANS | G41: 77 | H41: 12 | I41: =Tabla5[[#This Row],[CANTIDAD]]*Tabla5[[#This Row],[Prs/Caja]] -> 924 | J41: =Tabla5[[#This Row],[COSTO]]*Tabla5[[#This Row],[CANTIDAD]] -> 2316.93
B42: Imagen en Cartón | C42: 6 B | D42: 70*46*34 | E42: 26.7 | F42: NEXT & CO | G42: 20 | H42: 12 | I42: =Tabla5[[#This Row],[CANTIDAD]]*Tabla5[[#This Row],[Prs/Caja]] -> 240 | J42: =Tabla5[[#This Row],[COSTO]]*Tabla5[[#This Row],[CANTIDAD]] -> 534
A43: 7123 | B43: Imagen en Cartón | C43: Lacoste | D43: Chica | E43: 24.97 | F43: LACOSTE | H43: 12 | I43: =Tabla5[[#This Row],[CANTIDAD]]*Tabla5[[#This Row],[Prs/Caja]] -> 0 | J43: =Tabla5[[#This Row],[COSTO]]*Tabla5[[#This Row],[CANTIDAD]] -> 0
A44: 7124 | B44: Imagen en Cartón | C44: Lacoste | D44: Mediana | E44: 27.19 | F44: LACOSTE | H44: 12 | I44: =Tabla5[[#This Row],[CANTIDAD]]*Tabla5[[#This Row],[Prs/Caja]] -> 0 | J44: =Tabla5[[#This Row],[COSTO]]*Tabla5[[#This Row],[CANTIDAD]] -> 0
A45: 7125 | B45: Imagen en Cartón | C45: Lacoste | D45: Grande | E45: 28.96 | F45: LACOSTE | H45: 12 | I45: =Tabla5[[#This Row],[CANTIDAD]]*Tabla5[[#This Row],[Prs/Caja]] -> 0 | J45: =Tabla5[[#This Row],[COSTO]]*Tabla5[[#This Row],[CANTIDAD]] -> 0
A46: * | B46: Imagen en Cartón | C46: Forte | D46: Única | E46: 27.88 | F46: FORTE | G46: 52 | H46: 6 | I46: =Tabla5[[#This Row],[CANTIDAD]]*Tabla5[[#This Row],[Prs/Caja]] -> 312 | J46: =Tabla5[[#This Row],[COSTO]]*Tabla5[[#This Row],[CANTIDAD]] -> 1449.76 | K46: Inventario de cliente
G48: =SUM(Tabla5[CANTIDAD]) -> 2386 | I48: =SUM(I3:I47) -> 26078 | J48: =SUM(J3:J47) -> 73467.378

Sheet Etiquetas
A1: Descripción | B1: No. Ref | C1: Imagen | D1: Inventario 19.12.25 (pzs) | E1: Tipo | F1: Costo x pieza | G1: Total | H1: TIPO DE STOCK | I1: OBS | J1: Precios NO incluyen IVA
A2: Etiqueta Colgante Superga | B2: n/a | D2: 11505 | E2: Importación | F2: 0.7 | G2: =+Tabla3[[#This Row],[Costo x pieza]]*Tabla3[[#This Row],[Inventario 19.12.25 (pzs)]] -> 8053.5 | H2: OBSOLETO
A3: Sticker Superga | B3: n/a | D3: 21499 | E3: Importación | F3: 1 | G3: =+Tabla3[[#This Row],[Costo x pieza]]*Tabla3[[#This Row],[Inventario 19.12.25 (pzs)]] -> 21499 | H3: OBSOLETO
A4: Etiqueta suela Superga | B4: n/a | D4: 25960 | E4: Importación | F4: 0.11 | G4: =+Tabla3[[#This Row],[Costo x pieza]]*Tabla3[[#This Row],[Inventario 19.12.25 (pzs)]] -> 2855.6 | H4: OBSOLETO | I4: No se utiliza porque nos la mandaron con descripción de "piel"
A5: Shoe Filler Superga | B5: n/a | D5: 66265 | E5: Importación | F5: 0 | G5: =+Tabla3[[#This Row],[Costo x pieza]]*Tabla3[[#This Row],[Inventario 19.12.25 (pzs)]] -> 0 | H5: UTILIZABLE
A6: Etiqueta Colgante | B6: HT-3537 V1 | D6: 479 | E6: Importación | F6: 0.28 | G6: =+Tabla3[[#This Row],[Costo x pieza]]*Tabla3[[#This Row],[Inventario 19.12.25 (pzs)]] -> 134.12 | H6: OBSOLETO
A7: Etiqueta Colgante Skechers Lavado | B7: HT-3492 V1 | D7: 350 | E7: Importación | F7: 0.28 | G7: =+Tabla3[[#This Row],[Costo x pieza]]*Tabla3[[#This Row],[Inventario 19.12.25 (pzs)]] -> 98 | H7: OBSOLETO
A8: Sticker Chico | B8: ST-3491 20*60 MM | D8: 503 | E8: Importación | F8: 0.15 | G8: =+Tabla3[[#This Row],[Costo x pieza]]*Tabla3[[#This Row],[Inventario 19.12.25 (pzs)]] -> 75.45 | H8: OBSOLETO
A9: Sticker grande | B9: ST-3217 V1 5*3 CM | D9: 873 | E9: Importación | F9: 0.15 | G9: =+Tabla3[[#This Row],[Costo x pieza]]*Tabla3[[#This Row],[Inventario 19.12.25 (pzs)]] -> 130.95 | H9: OBSOLETO
A10: Cadenita | B10: 3 inches | D10: 407 | E10: Importación | F10: 0.37 | G10: =+Tabla3[[#This Row],[Costo x pieza]]*Tabla3[[#This Row],[Inventario 19.12.25 (pzs)]] -> 150.59 | H10: UTILIZABLE
A11: BOYS RUBBER BOTTOM STICKER Stickers | B11: PST-122250 | D11: 680 | E11: Importación | F11: 0.16 | G11: =+Tabla3[[#This Row],[Costo x pieza]]*Tabla3[[#This Row],[Inventario 19.12.25 (pzs)]] -> 108.8 | H11: OBSOLETO
A12: Etiqueta adhesiva Cocina | B12: SK-ST223 | D12: 14894 | E12: Nacional | F12: 0.2085 | G12: =+Tabla3[[#This Row],[Costo x pieza]]*Tabla3[[#This Row],[Inventario 19.12.25 (pzs)]] -> 3105.399 | H12: OBSOLETO
A13: Etiqueta Colgante Cocina | B13: SK-HT287 | D13: 9368 | E13: Nacional | F13: 0.409 | G13: =+Tabla3[[#This Row],[Costo x pieza]]*Tabla3[[#This Row],[Inventario 19.12.25 (pzs)]] -> 3831.512 | H13: OBSOLETO
A14: Etiqueta Colgante Skechers Arte | B14: HT 3578-N V1 | D14: 411 | E14: Importación | F14: 0.28 | G14: =+Tabla3[[#This Row],[Costo x pieza]]*Tabla3[[#This Row],[Inventario 19.12.25 (pzs)]] -> 115.08 | H14: OBSOLETO
A15: Etiqueta Colgante Skechers Lavado | B15: HT 3492-N V1 | D15: 10 | E15: Importación | F15: 0.28 | G15: =+Tabla3[[#This Row],[Costo x pieza]]*Tabla3[[#This Row],[Inventario 19.12.25 (pzs)]] -> 2.8 | H15: OBSOLETO
A16: Etiqueta Colgante Skechers Rubber | B16: PHT 104405 V1 | D16: 584 | E16: Importación | F16: 0.27 | G16: =+Tabla3[[#This Row],[Costo x pieza]]*Tabla3[[#This Row],[Inventario 19.12.25 (pzs)]] -> 157.68 | H16: OBSOLETO
... A27: ARCILLA | B27: N/A | D27: 600 | E27: Importación | F27: 6.92 | G27: =+Tabla3[[#This Row],[Costo x pieza]]*Tabla3[[#This Row],[Inventario 19.12.25 (pzs)]] -> 4152 | H27: UTILIZABLE
A28: Etiqueta colgante Categoría de Marca / Lacoste | B28: Sintético | D28: =300+220+800+185 -> 1505 | E28: Nacional | F28: 0.9 | G28: =+Tabla3[[#This Row],[Costo x pieza]]*Tabla3[[#This Row],[Inventario 19.12.25 (pzs)]] -> 1354.5 | H28: UTILIZABLE | I28: Sin costo por reposición Mal impresas / mal cortadas Extras
A29: Etiqueta colgante Categoría de Marca / Lacoste | B29: Piel | D29: =400+560+234+35 -> 1229 | E29: Nacional | F29: 0.9 | G29: =+Tabla3[[#This Row],[Costo x pieza]]*Tabla3[[#This Row],[Inventario 19.12.25 (pzs)]] -> 1106.1 | H29: UTILIZABLE | I29: Sin costo por reposición Mal impresas / mal cortadas Extras
A30: Etiqueta colgante Solidez de Color / Lacoste | B30: n/a | D30: =1000+552+560+119 -> 2231 | E30: Nacional | F30: 0.9 | G30: =+Tabla3[[#This Row],[Costo x pieza]]*Tabla3[[#This Row],[Inventario 19.12.25 (pzs)]] -> 2007.9 | H30: UTILIZABLE | I30: Sin costo por reposición Mal impresas / mal cortadas Extras
A31: Plastisol Lacoste | B31: Bco/Mno/Rojo | D31: 420 | E31: Nacional | F31: 1.5 | G31: =+Tabla3[[#This Row],[Costo x pieza]]*Tabla3[[#This Row],[Inventario 19.12.25 (pzs)]] -> 630 | H31: UTILIZABLE | I31: 250 prs sin costo
A32: ETIQUETA RFID | B32: n/a | D32: 317 | E32: Nacional | F32: 1.61 | G32: =+Tabla3[[#This Row],[Costo x pieza]]*Tabla3[[#This Row],[Inventario 19.12.25 (pzs)]] -> 510.37 | H32: OBSOLETO | I32: Etiquetas extras, sólo cobraron el costo de etiqueta sin impresión
A33: ETIQUETA RFID | B33: n/a | D33: 1261 | E33: Nacional | F33: 2.81 | G33: =+Tabla3[[#This Row],[Costo x pieza]]*Tabla3[[#This Row],[Inventario 19.12.25 (pzs)]] -> 3543.41 | H33: OBSOLETO | I33: Sobrantes
A34: Etiqueta colgante Ortholite | B34: n/a | D34: 7500 | E34: Importación | F34: 0 | G34: =+Tabla3[[#This Row],[Costo x pieza]]*Tabla3[[#This Row],[Inventario 19.12.25 (pzs)]] -> 0 | H34: UTILIZABLE | I34: viene con la plantilla
A35: Etiqueta INF QC | B35: Verde | D35: 176 | E35: Nacional | F35: 4 | G35: =+Tabla3[[#This Row],[Costo x pieza]]*Tabla3[[#This Row],[Inventario 19.12.25 (pzs)]] -> 704 | H35: UTILIZABLE
A36: Etiqueta INF QC | B36: Amarilla | D36: 111 | E36: Nacional | F36: 4 | G36: =+Tabla3[[#This Row],[Costo x pieza]]*Tabla3[[#This Row],[Inventario 19.12.25 (pzs)]] -> 444 | H36: UTILIZABLE
A37: Etiqueta Colgante HD | B37: n/a | D37: 960 | E37: Nacional | F37: 0.75 | G37: =+Tabla3[[#This Row],[Costo x pieza]]*Tabla3[[#This Row],[Inventario 19.12.25 (pzs)]] -> 720 | H37: UTILIZABLE
A38: Etiqueta colgante Polo | B38: n/a | D38: 8000 | E38: Nacional | F38: 0.31 | G38: =F38*D38 -> 2480 | H38: Revisar posible venta | I38: Etiqueta ene 2023 Revisión / Por mínimo de proveedor
A39: ETIQ. VANS OFF THE WALL | B39: n/a | D39: 141982 | E39: Importación | F39: 0 | G39: =+Tabla3[[#This Row],[Costo x pieza]]*Tabla3[[#This Row],[Inventario 19.12.25 (pzs)]] -> 0 | H39: Revisar posible venta | I39: Sin dato de costo
A40: ETIQ. VANS QC LABEL | B40: n/a | D40: 250000 | E40: Importación | F40: 0 | G40: =+Tabla3[[#This Row],[Costo x pieza]]*Tabla3[[#This Row],[Inventario 19.12.25 (pzs)]] -> 0 | H40: OBSOLETO | I40: Sin dato de costo
A41: STICKER DE PLANTILLA VANS 1.9*1.9cm_EXPO | B41: n/a | D41: 165364 | E41: Importación | F41: 0 | G41: =+Tabla3[[#This Row],[Costo x pieza]]*Tabla3[[#This Row],[Inventario 19.12.25 (pzs)]] -> 0 | H41: OBSOLETO | I41: Sin dato de costo
A42: Total | G42: =SUBTOTAL(109,Tabla3[Total]) -> 63647.386 | H42: =SUBTOTAL(103,Tabla3[TIPO DE STOCK]) -> 40
D45: =SUM(Tabla3[Inventario 19.12.25 (pzs)]) -> 760822 | G45: =SUM(G2:G41) -> 63647.386
